---- TRACE 8 start triplet_bench_lib.lua:358
0001  TGETS    2   0   0  ; "tee"
0002  KSHORT   4   2
0003  TGETS    5   0   1  ; "seq"
0004  TGETS    7   1   2  ; "values"
0005  CALL     5   0   2
0000  . FUNCF    4          ; triplet.lua:51
0001  . UGET     1   0      ; seq_gen
0002  . MOV      2   0
0003  . KSHORT   3   0
0004  . RET      1   4
0006  CALLM    2   2   1
0000  . FUNCF   15          ; triplet.lua:933
0001  . TNEW     4   0
0002  . TNEW     5   0
0003  . TNEW     6   0
0004  . KSHORT   7   1
0005  . MOV      8   0
0006  . KSHORT   9   1
0007  . FORI     7 => 0015
0008  . TNEW    11   0
0009  . TSETV   11   4  10
0010  . KSHORT  11   1
0011  . TSETV   11   5  10
0012  . KSHORT  11   0
0013  . TSETV   11   6  10
0014  . FORL     7 => 0008
---- TRACE 8 abort triplet.lua:938 -- inner loop in root trace

---- TRACE 8 start triplet.lua:937
0008  TNEW    11   0
0009  TSETV   11   4  10
0010  KSHORT  11   1
0011  TSETV   11   5  10
0012  KSHORT  11   0
0013  TSETV   11   6  10
0014  FORL     7 => 0008
---- TRACE 8 abort triplet.lua:943 -- leaving loop in root trace

---- TRACE 8 start 3/11 triplet.lua:926
0062  . TGETV   17   4  15
0063  . TSETV   10  17  16
0064  . FORL    12 => 0057
0065  . UGET    12   5      ; ACTIVE
0066  . MOV     13  10
0067  . RET     12   3
0019  ISNEP    8   0
0020  JMP     10 => 0022
0022  MOV      3   8
0023  ADDVV    7   7   9
0024  JMP      8 => 0014
0014  JLOOP    8   3
---- TRACE 8 IR
0001    [31mtab[m SLOAD  #12   PI
0002    [34mnum[m SLOAD  #13   PI
0003    [31mtab[m SLOAD  #14   PI
0004    [34mnum[m SLOAD  #15   PI
0005    [31mtab[m SLOAD  #16   PI
0006    [31mtab[m SLOAD  #17   PI
0007    [31mtab[m SLOAD  #18   PI
0008    [34mnum[m SLOAD  #19   PI
0009    [34mnum[m SLOAD  #20   PI
0010    [34mnum[m SLOAD  #21   PI
0011    [34mnum[m SLOAD  #22   PI
0012    [34mnum[m SLOAD  #23   PI
0013    [35mint[m SLOAD  #25   PI
0014    [34mnum[m SLOAD  #28   PI
....        SNAP   #0   [ ---- ---- ---- ---- ---- ---- ---- ---- ---- ---- [1mtriplet.lua:886[m [34mftsz[m|[31m0001[m [34m0002[m [31m0003[m [34m0004[m [31m0005[m [31m0006[m [31m0007[m [34m0008[m [34m0009[m [34m0010[m [34m0011[m [34m0012[m [35m+2  [m [35m0013[m [35m+1  [m [35m+2  [m [34m0014[m ]
0015    [35mint[m FLOAD  0005  tab.asize
0016 >  [35mint[m ABC    0015  [35m+2  [m
0017    p64 FLOAD  0005  tab.array
0018    p64 AREF   0017  [35m+2  [m
0019 >  [31mtab[m ALOAD  0018
0020 >  [35mint[m CONV   0014  [35mint[m.[34mnum[m index
0021    [35mint[m FLOAD  0019  tab.asize
0022 >  [35mint[m ULE    0021  0020
0023    [35mint[m FLOAD  0019  tab.hmask
0024 >  [35mint[m EQ     0023  [35m+0  [m
0025    [31mtab[m FLOAD  0019  tab.meta
0026 >  [31mtab[m EQ     0025  [31mNULL[m
0027 >  [34mnum[m EQ     0014  0014
0028    p64 NEWREF 0019  0014
0029    [34mnum[m HSTORE 0028  0011
....        SNAP   #1   [ ---- ---- ---- ---- ---- ---- ---- ---- ---- ---- [1mtriplet.lua:886[m [34mftsz[m|[31m0001[m [34m0002[m [31m0003[m [34m0004[m [31m0005[m [31m0006[m [31m0007[m [34m0008[m [34m0009[m [34m0010[m [34m0011[m [34m0012[m [35m+3  [m [35m0013[m [35m+1  [m [35m+3  [m ]
0030 >  [35mint[m LT     0013  [35m+3  [m
....        SNAP   #2   [ ---- ---- ---- ---- ---- ---- ---- ---- ---- ---- [1mtriplet.lua:886[m [34mftsz[m|---- ---- ---- ---- ---- ---- ---- ---- ---- ---- [34m0011[m ---- ]
0031 >  [34mnum[m SLOAD  #9    T
0032    [34mnum[m ADD    0031  0011
....        SNAP   #3   [ ---- ---- ---- ---- ---- [34m+1  [m ---- ---- ---- [34m0032[m ]
---- TRACE 8 stop -> 3

---- TRACE 9 start 3/17 triplet.lua:46
0005  . . KPRI     2   0
0006  . . RET1     2   2
0042  . ISNEP    9   0
0043  . JMP     11 => 0049
0044  . UGET    11   6      ; TEE_SHARED_DONE
0045  . KPRI    12   2
0046  . TSETV   12   2  11
0047  . KPRI    11   0
0048  . RET1    11   2
0019  ISNEP    8   0
0020  JMP     10 => 0022
0021  JMP      8 => 0025
0025  JLOOP    8   5
---- TRACE 9 IR
0001    [34mnum[m SLOAD  #9    PI
0002    [31mtab[m SLOAD  #12   PI
0003    [31mtab[m SLOAD  #14   PI
0004    [34mnum[m SLOAD  #15   PI
0005    [31mtab[m SLOAD  #16   PI
0006    [31mtab[m SLOAD  #17   PI
0007    [31mtab[m SLOAD  #18   PI
0008    [34mnum[m SLOAD  #19   PI
0009    [34mnum[m SLOAD  #20   PI
....        SNAP   #0   [ ---- ---- ---- ---- ---- [35m+1  [m ---- ---- ---- [34m0001[m [1mtriplet.lua:886[m [34mftsz[m|[31m0002[m [34m+1  [m [31m0003[m [34m0004[m [31m0005[m [31m0006[m [31m0007[m [34m0008[m [34m0009[m [1mtriplet.lua:43[m [34mftsz[m|---- ---- ]
0010    [35mint[m FLOAD  0003  tab.asize
0011 >  [35mint[m ABC    0010  [35m+4  [m
0012    p64 FLOAD  0003  tab.array
0013    p64 AREF   0012  [35m+4  [m
0014    [31mtab[m FLOAD  0003  tab.meta
0015 >  [31mtab[m EQ     0014  [31mNULL[m
0016    tru ASTORE 0013  true
....        SNAP   #1   [ ---- ---- ---- ---- ---- [34m+1  [m ---- ---- ---- [34m0001[m ]
---- TRACE 9 stop -> 5

---- TRACE 10 start 5/10 triplet.lua:902
0022  . KSHORT   7   1
0023  . KSHORT   8   0
0024  . TSETV    7   5   3
0025  . TSETV    8   6   3
0026  . UGET    11   5      ; ACTIVE
0027  . MOV     12  10
0028  . RET     11   3
0030  ISNEP    8   0
0031  JMP     10 => 0033
0033  MOV      6   8
0034  ADDVV    7   7   9
0035  JMP      8 => 0025
0025  JLOOP    8   5
---- TRACE 10 IR
0001    [34mnum[m SLOAD  #9    PI
0002    [34mnum[m SLOAD  #15   PI
0003    [31mtab[m SLOAD  #17   PI
0004    [31mtab[m SLOAD  #18   PI
0005    [34mnum[m SLOAD  #22   PI
....        SNAP   #0   [ ---- ---- ---- ---- ---- ---- ---- ---- [35m+1  [m [34m0001[m [1mtriplet.lua:886[m [34mftsz[m|---- ---- ---- [34m0002[m ---- [31m0003[m [31m0004[m ---- ---- ---- [34m0005[m ]
0006 >  [35mint[m CONV   0002  [35mint[m.[34mnum[m index
0007    [35mint[m FLOAD  0003  tab.asize
0008 >  [35mint[m ABC    0007  0006
0009    p64 FLOAD  0003  tab.array
0010    p64 AREF   0009  0006
0011    [31mtab[m FLOAD  0003  tab.meta
0012 >  [31mtab[m EQ     0011  [31mNULL[m
0013    [34mnum[m ASTORE 0010  [34m+1  [m
....        SNAP   #1   [ ---- ---- ---- ---- ---- ---- ---- ---- [35m+1  [m [34m0001[m [1mtriplet.lua:886[m [34mftsz[m|---- ---- ---- [34m0002[m ---- ---- [31m0004[m ---- [35m+0  [m ---- [34m0005[m ]
0014    [35mint[m FLOAD  0004  tab.asize
0015 >  [35mint[m ABC    0014  0006
0016    p64 FLOAD  0004  tab.array
0017    p64 AREF   0016  0006
0018    [31mtab[m FLOAD  0004  tab.meta
0019 >  [31mtab[m EQ     0018  [31mNULL[m
0020    [34mnum[m ASTORE 0017  [34m+0  [m
0021    [34mnum[m ADD    0005  0001
....        SNAP   #2   [ ---- ---- ---- ---- ---- ---- ---- ---- [34m+1  [m [34m0021[m ]
---- TRACE 10 stop -> 5

---- TRACE 11 start 5/1 triplet.lua:910
0029  . UGET     9   6      ; TEE_SHARED_DONE
0030  . TGETV    9   2   9
0031  . ISF          9
0032  . JMP     10 => 0035
0033  . KPRI     9   0
0034  . RET1     9   2
0030  ISNEP    8   0
0031  JMP     10 => 0033
0032  JMP      8 => 0036
0036  RET1     7   2
0099  ADDVV   13  13  18
0100  FORL    14 => 0097
0097  MOV     18  12
0098  CALL    18   2   1
0000  . FUNCF    5          ; triplet_trace.lua:19
0001  . UGET     0   0      ; lib
0002  . TGETS    0   0   0  ; "run_once"
0003  . UGET     2   1      ; T
0004  . UGET     3   2      ; scenario_name
0005  . UGET     4   3      ; payload
0006  . CALLT    0   4
0000  . FUNCF    7          ; triplet_bench_lib.lua:426
0001  . UGET     3   0      ; M
0002  . TGETS    3   3   0  ; "get_scenario"
0003  . MOV      5   1
0004  . CALL     3   2   2
0000  . . FUNCF    8          ; triplet_bench_lib.lua:413
0001  . . UGET     1   0      ; scenarios
0002  . . TGETV    1   1   0
0003  . . IST          1
0004  . . JMP      2 => 0013
0013  . . RET1     1   2
0005  . TGETS    3   3   1  ; "run_once"
0006  . MOV      5   0
0007  . MOV      6   2
0008  . CALLT    3   3
0000  . FUNCF    8          ; triplet_bench_lib.lua:358
0001  . TGETS    2   0   0  ; "tee"
0002  . KSHORT   4   2
0003  . TGETS    5   0   1  ; "seq"
0004  . TGETS    7   1   2  ; "values"
0005  . CALL     5   0   2
0000  . . FUNCF    4          ; triplet.lua:51
0001  . . UGET     1   0      ; seq_gen
0002  . . MOV      2   0
0003  . . KSHORT   3   0
0004  . . RET      1   4
0006  . CALLM    2   2   1
0000  . . FUNCF   15          ; triplet.lua:933
0001  . . TNEW     4   0
0002  . . TNEW     5   0
0003  . . TNEW     6   0
0004  . . KSHORT   7   1
0005  . . MOV      8   0
0006  . . KSHORT   9   1
0007  . . FORI     7 => 0015
0008  . . TNEW    11   0
0009  . . TSETV   11   4  10
0010  . . KSHORT  11   1
0011  . . TSETV   11   5  10
0012  . . KSHORT  11   0
0013  . . TSETV   11   6  10
0014  . . FORL     7 => 0008
0008  . . TNEW    11   0
0009  . . TSETV   11   4  10
0010  . . KSHORT  11   1
0011  . . TSETV   11   5  10
0012  . . KSHORT  11   0
0013  . . TSETV   11   6  10
0014  . . FORL     7 => 0008
0015  . . TDUP     7   0
0016  . . TSETB    1   7   1
0017  . . TSETB    2   7   2
0018  . . TSETB    3   7   3
0019  . . TSETB    4   7   5
0020  . . TSETB    5   7   6
0021  . . TSETB    6   7   7
0022  . . TSETB    0   7   8
0023  . . TNEW     8   0
0024  . . KSHORT   9   1
0025  . . MOV     10   0
0026  . . KSHORT  11   1
0027  . . FORI     9 => 0037
0028  . . TDUP    13   1
0029  . . UGET    14   0      ; tee_branch_gen
0030  . . TSETB   14  13   1
0031  . . TNEW    14   3
0032  . . TSETB    7  14   1
0033  . . TSETB   12  14   2
0034  . . TSETB   14  13   2
0035  . . TSETV   13   8  12
0036  . . FORL     9 => 0028
0028  . . TDUP    13   1
0029  . . UGET    14   0      ; tee_branch_gen
0030  . . TSETB   14  13   1
0031  . . TNEW    14   3
0032  . . TSETB    7  14   1
0033  . . TSETB   12  14   2
0034  . . TSETB   14  13   2
0035  . . TSETV   13   8  12
0036  . . FORL     9 => 0028
0037  . . RET1     8   2
0007  . UGET     3   0      ; sum_tee_skewed
0008  . MOV      5   2
0009  . CALLT    3   2
0000  . FUNCF   12          ; triplet_bench_lib.lua:133
0001  . TGETB    1   0   1
0002  . TGETB    1   1   1
0003  . TGETB    2   0   1
0004  . TGETB    2   2   2
0005  . TGETB    3   0   1
0006  . TGETB    3   3   3
0007  . TGETB    4   0   2
0008  . TGETB    4   4   1
0009  . TGETB    5   0   2
0010  . TGETB    5   5   2
0011  . TGETB    6   0   2
0012  . TGETB    6   6   3
0013  . KSHORT   7   0
0014  . JLOOP    8   3
---- TRACE 11 IR
0001    [31mtab[m SLOAD  #12   PI
0002    [34mnum[m SLOAD  #13   PI
0003    [31mtab[m SLOAD  #14   PI
0004    [34mnum[m SLOAD  #15   PI
0005    [31mtab[m SLOAD  #16   PI
0006    [31mtab[m SLOAD  #17   PI
0007    [31mtab[m SLOAD  #18   PI
0008    [34mnum[m SLOAD  #19   PI
0009    [34mnum[m SLOAD  #20   PI
....        SNAP   #0   [ ---- ---- ---- ---- ---- ---- ---- ---- ---- ---- [1mtriplet.lua:886[m [34mftsz[m|[31m0001[m [34m0002[m [31m0003[m [34m0004[m [31m0005[m [31m0006[m [31m0007[m [34m0008[m [34m0009[m ]
0010    [35mint[m FLOAD  0003  tab.asize
0011 >  [35mint[m ABC    0010  [35m+4  [m
0012    p64 FLOAD  0003  tab.array
0013    p64 AREF   0012  [35m+4  [m
0014 >  tru ALOAD  0013
0015 >  [34mnum[m SLOAD  #9    T
....        SNAP   #1   [ ---- ---- ---- ---- ---- ---- ---- ---- ---- ---- ]
0016 >  p64 RETF   proto: 0x7f3de4f1c728  [0x7f3de4f1c91c]
....        SNAP   #2   [ ---- ---- ---- ---- ---- ---- ---- ---- ---- ---- ---- ---- ---- ---- ---- ---- ---- ---- ---- ---- [34m0015[m ]
0017 >  [34mnum[m SLOAD  #15   T
0018    [34mnum[m ADD    0017  0015
0019    [34mnum[m SLOAD  #17   RI
0020    [34mnum[m SLOAD  #16   I
0021    [34mnum[m ADD    0020  [34m+1  [m
....        SNAP   #3   [ ---- ---- ---- ---- ---- ---- ---- ---- ---- ---- ---- ---- ---- ---- ---- [34m0018[m ]
0022 >  [34mnum[m LE     0021  0019
....        SNAP   #4   [ ---- ---- ---- ---- ---- ---- ---- ---- ---- ---- ---- ---- ---- ---- ---- [34m0018[m [34m0021[m [34m0019[m ---- ---- ]
0023 >  [1mfun[m SLOAD  #14   T
0024 >  [1mfun[m EQ     0023  [1mtriplet_trace.lua:19[m
0025    p64 UREFO  [1mtriplet_trace.lua:19[m  #0  
0026    p64 ADD    0025  [35m-16 [m
0027 >  p64 EQ     0026  0000
0028 >  [31mtab[m SLOAD  #4    T
0029    [35mint[m FLOAD  0028  tab.hmask
0030 >  [35mint[m EQ     0029  [35m+15 [m
0031    p64 FLOAD  0028  tab.node
0032 >  p64 HREFK  0031  [32m"run_once"[m @11
0033 >  [1mfun[m HLOAD  0032
0034    p64 UREFO  [1mtriplet_trace.lua:19[m  #1  
0035    p64 ADD    0034  [35m-80 [m
0036 >  p64 EQ     0035  0000
0037 >  [31mtab[m SLOAD  #12   T
0038    p64 UREFO  [1mtriplet_trace.lua:19[m  #3  
0039    p64 ADD    0038  [35m-88 [m
0040 >  p64 EQ     0039  0000
0041 >  [31mtab[m SLOAD  #13   T
0042 >  [1mfun[m EQ     0033  [1mtriplet_bench_lib.lua:426[m
0043    p64 UREFC  [1mtriplet_bench_lib.lua:426[m  #0  
0044 >  [31mtab[m ULOAD  0043
0045    [35mint[m FLOAD  0044  tab.hmask
0046 >  [35mint[m EQ     0045  [35m+15 [m
0047    p64 FLOAD  0044  tab.node
0048 >  p64 HREFK  0047  [32m"get_scenario"[m @13
0049 >  [1mfun[m HLOAD  0048
0050 >  [1mfun[m EQ     0049  [1mtriplet_bench_lib.lua:413[m
0051    p64 UREFC  [1mtriplet_bench_lib.lua:413[m  #0  
0052 >  [31mtab[m ULOAD  0051
0053    [35mint[m FLOAD  0052  tab.hmask
0054 >  [35mint[m EQ     0053  [35m+15 [m
0055    p64 FLOAD  0052  tab.node
0056 >  p64 HREFK  0055  [32m"drain_tee_skewed"[m @14
0057 >  [31mtab[m HLOAD  0056
0058    [35mint[m FLOAD  0057  tab.hmask
0059 >  [35mint[m EQ     0058  [35m+7  [m
0060    p64 FLOAD  0057  tab.node
0061 >  p64 HREFK  0060  [32m"run_once"[m @1
0062 >  [1mfun[m HLOAD  0061
0063 >  [1mfun[m EQ     0062  [1mtriplet_bench_lib.lua:358[m
0064    [35mint[m FLOAD  0037  tab.hmask
0065 >  [35mint[m EQ     0064  [35m+63 [m
0066    p64 FLOAD  0037  tab.node
0067 >  p64 HREFK  0066  [32m"tee"[m @20
0068 >  [1mfun[m HLOAD  0067
0069 >  p64 HREFK  0066  [32m"seq"[m @44
0070 >  [1mfun[m HLOAD  0069
0071    [35mint[m FLOAD  0041  tab.hmask
0072 >  [35mint[m EQ     0071  [35m+1  [m
0073    p64 FLOAD  0041  tab.node
0074 >  p64 HREFK  0073  [32m"values"[m @1
0075 >  [31mtab[m HLOAD  0074
0076 >  [1mfun[m EQ     0070  [1mtriplet.lua:51[m
0077 >  [1mfun[m EQ     0068  [1mtriplet.lua:933[m
0078 >  [31mtab[m TNEW   #0    #0  
0079 >  [31mtab[m TNEW   #0    #0  
0080 >  [31mtab[m TNEW   #0    #0  
....        SNAP   #5   [ ---- ---- ---- ---- ---- ---- ---- ---- ---- ---- ---- ---- ---- ---- ---- [34m0018[m [34m0021[m [34m0019[m ---- ---- [1mtriplet_bench_lib.lua:358[m [34mftsz[m|[31m0037[m [31m0041[m [1mtriplet.lua:933[m [34mftsz[m|[35m+2  [m [1mtriplet.lua:43[m [31m0075[m [35m+0  [m [31m0078[m [31m0079[m [31m0080[m [35m+1  [m [35m+2  [m [35m+1  [m [35m+1  [m ]
0081 >  [31mtab[m TNEW   #0    #0  
0082    p64 NEWREF 0078  [34m+1  [m
0083    [31mtab[m HSTORE 0082  0081
0084    p64 NEWREF 0079  [34m+1  [m
0085    [34mnum[m HSTORE 0084  [34m+1  [m
0086    p64 NEWREF 0080  [34m+1  [m
0087    [34mnum[m HSTORE 0086  [34m+0  [m
....        SNAP   #6   [ ---- ---- ---- ---- ---- ---- ---- ---- ---- ---- ---- ---- ---- ---- ---- [34m0018[m [34m0021[m [34m0019[m ---- ---- [1mtriplet_bench_lib.lua:358[m [34mftsz[m|[31m0037[m [31m0041[m [1mtriplet.lua:933[m [34mftsz[m|[35m+2  [m [1mtriplet.lua:43[m [31m0075[m [35m+0  [m [31m0078[m [31m0079[m [31m0080[m [35m+2  [m [35m+2  [m [35m+1  [m [35m+2  [m ]
0088 >  [31mtab[m TNEW   #0    #0  
0089    [35mint[m FLOAD  0078  tab.asize
0090 >  [35mint[m ABC    0089  [35m+2  [m
0091    p64 FLOAD  0078  tab.array
0092    p64 AREF   0091  [35m+2  [m
0093    [31mtab[m ASTORE 0092  0088
....        SNAP   #7   [ ---- ---- ---- ---- ---- ---- ---- ---- ---- ---- ---- ---- ---- ---- ---- [34m0018[m [34m0021[m [34m0019[m ---- ---- [1mtriplet_bench_lib.lua:358[m [34mftsz[m|[31m0037[m [31m0041[m [1mtriplet.lua:933[m [34mftsz[m|[35m+2  [m [1mtriplet.lua:43[m [31m0075[m [35m+0  [m [31m0078[m [31m0079[m [31m0080[m [35m+2  [m [35m+2  [m [35m+1  [m [35m+2  [m ---- ]
0094    [35mint[m FLOAD  0079  tab.asize
0095 >  [35mint[m ABC    0094  [35m+2  [m
0096    p64 FLOAD  0079  tab.array
0097    p64 AREF   0096  [35m+2  [m
0098    [34mnum[m ASTORE 0097  [34m+1  [m
....        SNAP   #8   [ ---- ---- ---- ---- ---- ---- ---- ---- ---- ---- ---- ---- ---- ---- ---- [34m0018[m [34m0021[m [34m0019[m ---- ---- [1mtriplet_bench_lib.lua:358[m [34mftsz[m|[31m0037[m [31m0041[m [1mtriplet.lua:933[m [34mftsz[m|[35m+2  [m [1mtriplet.lua:43[m [31m0075[m [35m+0  [m [31m0078[m [31m0079[m [31m0080[m [35m+2  [m [35m+2  [m [35m+1  [m [35m+2  [m ---- ]
0099    [35mint[m FLOAD  0080  tab.asize
0100 >  [35mint[m ABC    0099  [35m+2  [m
0101    p64 FLOAD  0080  tab.array
0102    p64 AREF   0101  [35m+2  [m
0103    [34mnum[m ASTORE 0102  [34m+0  [m
....        SNAP   #9   [ ---- ---- ---- ---- ---- ---- ---- ---- ---- ---- ---- ---- ---- ---- ---- [34m0018[m [34m0021[m [34m0019[m ---- ---- [1mtriplet_bench_lib.lua:358[m [34mftsz[m|[31m0037[m [31m0041[m [1mtriplet.lua:933[m [34mftsz[m|[35m+2  [m [1mtriplet.lua:43[m [31m0075[m [35m+0  [m [31m0078[m [31m0079[m [31m0080[m ]
0104 >  [31mtab[m TDUP   [31m{0x7f3de4f28158}[m
0105    p64 FLOAD  0104  tab.array
0106    p64 AREF   0105  [35m+1  [m
0107    [1mfun[m ASTORE 0106  [1mtriplet.lua:43[m
0108    p64 AREF   0105  [35m+2  [m
0109    [31mtab[m ASTORE 0108  0075
0110    p64 AREF   0105  [35m+3  [m
0111    [34mnum[m ASTORE 0110  [34m+0  [m
0112    p64 AREF   0105  [35m+5  [m
0113    [31mtab[m ASTORE 0112  0078
0114    p64 AREF   0105  [35m+6  [m
0115    [31mtab[m ASTORE 0114  0079
0116    p64 AREF   0105  [35m+7  [m
0117    [31mtab[m ASTORE 0116  0080
0118    p64 AREF   0105  [35m+8  [m
0119    [34mnum[m ASTORE 0118  [34m+2  [m
....        SNAP   #10  [ ---- ---- ---- ---- ---- ---- ---- ---- ---- ---- ---- ---- ---- ---- ---- [34m0018[m [34m0021[m [34m0019[m ---- ---- [1mtriplet_bench_lib.lua:358[m [34mftsz[m|[31m0037[m [31m0041[m [1mtriplet.lua:933[m [34mftsz[m|[35m+2  [m [1mtriplet.lua:43[m [31m0075[m [35m+0  [m [31m0078[m [31m0079[m [31m0080[m [31m0104[m ]
0120 >  [31mtab[m TNEW   #0    #0  
....        SNAP   #11  [ ---- ---- ---- ---- ---- ---- ---- ---- ---- ---- ---- ---- ---- ---- ---- [34m0018[m [34m0021[m [34m0019[m ---- ---- [1mtriplet_bench_lib.lua:358[m [34mftsz[m|[31m0037[m [31m0041[m [1mtriplet.lua:933[m [34mftsz[m|[35m+2  [m [1mtriplet.lua:43[m [31m0075[m [35m+0  [m [31m0078[m [31m0079[m [31m0080[m [31m0104[m [31m0120[m [35m+1  [m [35m+2  [m [35m+1  [m [35m+1  [m ]
0121 >  [31mtab[m TDUP   [31m{0x7f3de4f2ae10}[m
0122    p64 FLOAD  0121  tab.array
0123    p64 AREF   0122  [35m+1  [m
0124    [1mfun[m ASTORE 0123  [1mtriplet.lua:886[m
....        SNAP   #12  [ ---- ---- ---- ---- ---- ---- ---- ---- ---- ---- ---- ---- ---- ---- ---- [34m0018[m [34m0021[m [34m0019[m ---- ---- [1mtriplet_bench_lib.lua:358[m [34mftsz[m|[31m0037[m [31m0041[m [1mtriplet.lua:933[m [34mftsz[m|[35m+2  [m [1mtriplet.lua:43[m [31m0075[m [35m+0  [m [31m0078[m [31m0079[m [31m0080[m [31m0104[m [31m0120[m [35m+1  [m [35m+2  [m [35m+1  [m [35m+1  [m [31m0121[m ---- ]
0125 >  [31mtab[m TNEW   #3    #0  
0126    p64 FLOAD  0125  tab.array
0127    p64 AREF   0126  [35m+1  [m
0128    [31mtab[m ASTORE 0127  0104
0129    p64 AREF   0126  [35m+2  [m
0130    [34mnum[m ASTORE 0129  [34m+1  [m
0131    p64 AREF   0122  [35m+2  [m
0132    [31mtab[m ASTORE 0131  0125
0133    p64 NEWREF 0120  [34m+1  [m
0134    [31mtab[m HSTORE 0133  0121
....        SNAP   #13  [ ---- ---- ---- ---- ---- ---- ---- ---- ---- ---- ---- ---- ---- ---- ---- [34m0018[m [34m0021[m [34m0019[m ---- ---- [1mtriplet_bench_lib.lua:358[m [34mftsz[m|[31m0037[m [31m0041[m [1mtriplet.lua:933[m [34mftsz[m|[35m+2  [m [1mtriplet.lua:43[m [31m0075[m [35m+0  [m [31m0078[m [31m0079[m [31m0080[m [31m0104[m [31m0120[m [35m+2  [m [35m+2  [m [35m+1  [m [35m+2  [m ]
0135 >  [31mtab[m TDUP   [31m{0x7f3de4f2ae10}[m
0136    p64 FLOAD  0135  tab.array
0137    p64 AREF   0136  [35m+1  [m
0138    [1mfun[m ASTORE 0137  [1mtriplet.lua:886[m
....        SNAP   #14  [ ---- ---- ---- ---- ---- ---- ---- ---- ---- ---- ---- ---- ---- ---- ---- [34m0018[m [34m0021[m [34m0019[m ---- ---- [1mtriplet_bench_lib.lua:358[m [34mftsz[m|[31m0037[m [31m0041[m [1mtriplet.lua:933[m [34mftsz[m|[35m+2  [m [1mtriplet.lua:43[m [31m0075[m [35m+0  [m [31m0078[m [31m0079[m [31m0080[m [31m0104[m [31m0120[m [35m+2  [m [35m+2  [m [35m+1  [m [35m+2  [m [31m0135[m ---- ]
0139 >  [31mtab[m TNEW   #3    #0  
0140    p64 FLOAD  0139  tab.array
0141    p64 AREF   0140  [35m+1  [m
0142    [31mtab[m ASTORE 0141  0104
0143    p64 AREF   0140  [35m+2  [m
0144    [34mnum[m ASTORE 0143  [34m+2  [m
0145    p64 AREF   0136  [35m+2  [m
0146    [31mtab[m ASTORE 0145  0139
....        SNAP   #15  [ ---- ---- ---- ---- ---- ---- ---- ---- ---- ---- ---- ---- ---- ---- ---- [34m0018[m [34m0021[m [34m0019[m ---- ---- [1mtriplet_bench_lib.lua:358[m [34mftsz[m|[31m0037[m [31m0041[m [1mtriplet.lua:933[m [34mftsz[m|[35m+2  [m [1mtriplet.lua:43[m [31m0075[m [35m+0  [m [31m0078[m [31m0079[m [31m0080[m [31m0104[m [31m0120[m [35m+2  [m [35m+2  [m [35m+1  [m [35m+2  [m [31m0135[m ---- ]
0147    [35mint[m FLOAD  0120  tab.asize
0148 >  [35mint[m ABC    0147  [35m+2  [m
0149    p64 FLOAD  0120  tab.array
0150    p64 AREF   0149  [35m+2  [m
0151    [31mtab[m ASTORE 0150  0135
....        SNAP   #16  [ ---- ---- ---- ---- ---- ---- ---- ---- ---- ---- ---- ---- ---- ---- ---- [34m0018[m [34m0021[m [34m0019[m ---- ---- [1mtriplet_bench_lib.lua:358[m [34mftsz[m|[31m0037[m [31m0041[m [1mtriplet.lua:933[m [34mftsz[m|---- ---- ---- ---- ---- ---- ---- ---- [31m0120[m ]
0152    p64 AREF   0149  [35m+1  [m
0153 >  [31mtab[m ALOAD  0152
0154    [35mint[m FLOAD  0153  tab.asize
0155 >  [35mint[m ABC    0154  [35m+3  [m
0156    p64 FLOAD  0153  tab.array
0157    p64 AREF   0156  [35m+1  [m
0158 >  [1mfun[m ALOAD  0157
0159    p64 AREF   0156  [35m+2  [m
0160 >  [31mtab[m ALOAD  0159
0161    p64 AREF   0156  [35m+3  [m
0162 >  [34mnum[m ALOAD  0161
0163    p64 AREF   0136  [35m+3  [m
....        SNAP   #17  [ ---- ---- ---- ---- ---- ---- ---- ---- ---- ---- ---- ---- ---- ---- ---- [34m0018[m [34m0021[m [34m0019[m ---- ---- [1mtriplet_bench_lib.lua:133[m [34mftsz[m|[31m0120[m [1m0158[m [31m0160[m [34m0162[m [1mtriplet.lua:886[m [31m0139[m [34m+0  [m [34m+0  [m ]
---- TRACE 11 stop -> 3

---- TRACE 12 start triplet_trace.lua:31
0097  MOV     18  12
0098  CALL    18   2   1
0000  . FUNCF    5          ; triplet_trace.lua:19
0001  . UGET     0   0      ; lib
0002  . TGETS    0   0   0  ; "run_once"
0003  . UGET     2   1      ; T
0004  . UGET     3   2      ; scenario_name
0005  . UGET     4   3      ; payload
0006  . CALLT    0   4
0000  . FUNCF    7          ; triplet_bench_lib.lua:426
0001  . UGET     3   0      ; M
0002  . TGETS    3   3   0  ; "get_scenario"
0003  . MOV      5   1
0004  . CALL     3   2   2
0000  . . FUNCF    8          ; triplet_bench_lib.lua:413
0001  . . UGET     1   0      ; scenarios
0002  . . TGETV    1   1   0
0003  . . IST          1
0004  . . JMP      2 => 0013
0013  . . RET1     1   2
0005  . TGETS    3   3   1  ; "run_once"
0006  . MOV      5   0
0007  . MOV      6   2
0008  . CALLT    3   3
0000  . FUNCF    8          ; triplet_bench_lib.lua:358
0001  . TGETS    2   0   0  ; "tee"
0002  . KSHORT   4   2
0003  . TGETS    5   0   1  ; "seq"
0004  . TGETS    7   1   2  ; "values"
0005  . CALL     5   0   2
0000  . . FUNCF    4          ; triplet.lua:51
0001  . . UGET     1   0      ; seq_gen
0002  . . MOV      2   0
0003  . . KSHORT   3   0
0004  . . RET      1   4
0006  . CALLM    2   2   1
0000  . . FUNCF   15          ; triplet.lua:933
0001  . . TNEW     4   0
0002  . . TNEW     5   0
0003  . . TNEW     6   0
0004  . . KSHORT   7   1
0005  . . MOV      8   0
0006  . . KSHORT   9   1
0007  . . FORI     7 => 0015
0008  . . TNEW    11   0
0009  . . TSETV   11   4  10
0010  . . KSHORT  11   1
0011  . . TSETV   11   5  10
0012  . . KSHORT  11   0
0013  . . TSETV   11   6  10
0014  . . FORL     7 => 0008
---- TRACE 12 abort triplet.lua:938 -- inner loop in root trace

---- TRACE 12 start triplet_bench_lib.lua:133
0001  TGETB    1   0   1
0002  TGETB    1   1   1
0003  TGETB    2   0   1
0004  TGETB    2   2   2
0005  TGETB    3   0   1
0006  TGETB    3   3   3
0007  TGETB    4   0   2
0008  TGETB    4   4   1
0009  TGETB    5   0   2
0010  TGETB    5   5   2
0011  TGETB    6   0   2
0012  TGETB    6   6   3
0013  KSHORT   7   0
0014  JLOOP    8   3
---- TRACE 12 abort triplet_bench_lib.lua:139 -- inner loop in root trace

---- TRACE 12 start triplet_bench_lib.lua:426
0001  UGET     3   0      ; M
0002  TGETS    3   3   0  ; "get_scenario"
0003  MOV      5   1
0004  CALL     3   2   2
0000  . FUNCF    8          ; triplet_bench_lib.lua:413
0001  . UGET     1   0      ; scenarios
0002  . TGETV    1   1   0
0003  . IST          1
0004  . JMP      2 => 0013
0013  . RET1     1   2
0005  TGETS    3   3   1  ; "run_once"
0006  MOV      5   0
0007  MOV      6   2
0008  CALLT    3   3
0000  FUNCF    8          ; triplet_bench_lib.lua:358
0001  TGETS    2   0   0  ; "tee"
0002  KSHORT   4   2
0003  TGETS    5   0   1  ; "seq"
0004  TGETS    7   1   2  ; "values"
0005  CALL     5   0   2
0000  . FUNCF    4          ; triplet.lua:51
0001  . UGET     1   0      ; seq_gen
0002  . MOV      2   0
0003  . KSHORT   3   0
0004  . RET      1   4
0006  CALLM    2   2   1
0000  . FUNCF   15          ; triplet.lua:933
0001  . TNEW     4   0
0002  . TNEW     5   0
0003  . TNEW     6   0
0004  . KSHORT   7   1
0005  . MOV      8   0
0006  . KSHORT   9   1
0007  . FORI     7 => 0015
0008  . TNEW    11   0
0009  . TSETV   11   4  10
0010  . KSHORT  11   1
0011  . TSETV   11   5  10
0012  . KSHORT  11   0
0013  . TSETV   11   6  10
0014  . FORL     7 => 0008
---- TRACE 12 abort triplet.lua:938 -- inner loop in root trace

---- TRACE 12 start 11/3 triplet_trace.lua:35
0101  GGET    14  26      ; "print"
0102  GGET    16  14      ; "string"
0103  TGETS   16  16  15  ; "format"
0104  KSTR    18  27      ; "wrote trace dump to %s  impl=%s scenario"~
0105  MOV     19   9
0106  MOV     20   3
0107  MOV     21   4
0108  MOV     22   5
0109  MOV     23   6
0110  GGET    24  28      ; "tostring"
0111  MOV     26  13
0112  CALL    24   0   2
0000  . FUNCC               ; tostring
0113  CALLM   16   0   6
0000  . FUNCC               ; string.format
0114  CALLM   14   1   0
0000  . FUNCC               ; print
---- TRACE 12 IR
0001    [34mnum[m SLOAD  #15   PI
....        SNAP   #0   [ ---- ---- ---- ---- ---- ---- ---- ---- ---- ---- ---- ---- ---- ---- ---- [34m0001[m ]
0002    [1mfun[m SLOAD  #0    R
0003    [31mtab[m FLOAD  0002  func.env
0004    [35mint[m FLOAD  0003  tab.hmask
0005 >  [35mint[m EQ     0004  [35m+63 [m
0006    p64 FLOAD  0003  tab.node
0007 >  p64 HREFK  0006  [32m"print"[m @12
0008 >  [1mfun[m HLOAD  0007
0009 >  p64 HREFK  0006  [32m"string"[m @42
0010 >  [31mtab[m HLOAD  0009
0011    [35mint[m FLOAD  0010  tab.hmask
0012 >  [35mint[m EQ     0011  [35m+15 [m
0013    p64 FLOAD  0010  tab.node
0014 >  p64 HREFK  0013  [32m"format"[m @14
0015 >  [1mfun[m HLOAD  0014
0016 >  [32mstr[m SLOAD  #11   T
0017 >  [32mstr[m SLOAD  #5    T
0018 >  [32mstr[m SLOAD  #6    T
0019 >  [34mnum[m SLOAD  #7    T
0020 >  [34mnum[m SLOAD  #8    T
0021 >  p64 HREFK  0006  [32m"tostring"[m @1
0022 >  [1mfun[m HLOAD  0021
0023 >  [1mfun[m EQ     0022  [1mtostring[m
0024    [32mstr[m TOSTR  0001  NUM
0025 >  [1mfun[m EQ     0015  [1mstring.format[m
0026    p64 BUFHDR [0x7f3de4f104a8]  RESET
0027 >  p64 BUFPUT 0026  [32m"wrote trace dump to "[m
0028 >  p64 BUFPUT 0027  0016
0029 >  p64 BUFPUT 0028  [32m"  impl="[m
0030 >  p64 BUFPUT 0029  0017
0031 >  p64 BUFPUT 0030  [32m" scenario="[m
0032 >  p64 BUFPUT 0031  0018
0033 >  p64 BUFPUT 0032  [32m" n="[m
0036 >  p64 CALLL  lj_strfmt_putfnum_int  (0033 [35m+3  [m 0019)
0037 >  p64 BUFPUT 0036  [32m" iters="[m
0040 >  p64 CALLL  lj_strfmt_putfnum_int  (0037 [35m+3  [m 0020)
0041 >  p64 BUFPUT 0040  [32m" checksum="[m
0042 >  p64 BUFPUT 0041  0024
0043 >  [32mstr[m BUFSTR 0042  0026
0044 >  [1mfun[m EQ     0008  [1mprint[m
....        SNAP   #1   [ ---- ---- ---- ---- ---- ---- ---- ---- ---- ---- ---- ---- ---- ---- ---- [34m0001[m trace: 0x7f3de4f1bd38 [34m+0x1.592c0a1bec74p-1028[m [34mcontpc[m [1mprint[m [34mftsz[m|[32m0043[m ]
---- TRACE 12 stop -> stitch

