---- TRACE 9 start triplet_old.lua:570
0010  TNEW    10   0
0011  TSETV   10   4   9
0012  FORL     6 => 0010
---- TRACE 9 abort triplet_old.lua:586 -- leaving loop in root trace

---- TRACE 9 start triplet_old.lua:589
0019  TDUP    12   7
0020  TSETB    6  12   1
0021  TDUP    13   5
0022  TGETV   14   4  11
0023  TSETS   14  13   6  ; "buf"
0024  TSETB   13  12   2
0025  TSETV   12   7  11
0026  FORL     8 => 0019
---- TRACE 9 abort triplet_old.lua:592 -- leaving loop in root trace

---- TRACE 9 start triplet_bench_lib.lua:133
0001  TGETB    1   0   1
0002  TGETB    1   1   1
0003  TGETB    2   0   1
0004  TGETB    2   2   2
0005  TGETB    3   0   1
0006  TGETB    3   3   3
0007  TGETB    4   0   2
0008  TGETB    4   4   1
0009  TGETB    5   0   2
0010  TGETB    5   5   2
0011  TGETB    6   0   2
0012  TGETB    6   6   3
0013  KSHORT   7   0
0014  JLOOP    8   3
---- TRACE 9 abort triplet_bench_lib.lua:139 -- inner loop in root trace

---- TRACE 9 start 3/0 triplet_bench_lib.lua:139
0015  MOV      8   1
0016  MOV     10   2
0017  MOV     11   3
0018  CALL     8   3   3
0000  . FUNCF   10          ; triplet_old.lua:572
0001  . TGETS    2   0   0  ; "buf"
0002  . LEN      2   2
0003  . KSHORT   3   0
0004  . ISGE     3   2
0005  . JMP      2 => 0013
0013  . UGET     2   0      ; state
0014  . TGETS    2   2   3  ; "g"
0015  . UGET     4   0      ; state
0016  . TGETS    4   4   4  ; "p"
0017  . UGET     5   0      ; state
0018  . TGETS    5   5   5  ; "c"
0019  . CALL     2   3   3
0000  . . FUNCF    4          ; triplet_old.lua:33
0001  . . ADDVN    1   1   0  ; 1
0002  . . LEN      2   0
0003  . . ISGE     2   1
0004  . . JMP      2 => 0007
0007  . . MOV      2   1
0008  . . TGETV    3   0   1
0009  . . RET      2   3
0020  . ISNEP    2   0
0021  . JMP      4 => 0024
0024  . UGET     4   0      ; state
0025  . TSETS    2   4   5  ; "c"
0026  . KSHORT   4   1
0027  . UGET     5   1      ; n
0028  . KSHORT   6   1
0029  . FORI     4 => 0043
0030  . UGET     8   2      ; buffers
0031  . TGETV    8   8   7
0032  . TGETS    9   0   0  ; "buf"
0033  . ISEQV    8   9
0034  . JMP      8 => 0042
0042  . FORL     4 => 0030
0030  . UGET     8   2      ; buffers
0031  . TGETV    8   8   7
0032  . TGETS    9   0   0  ; "buf"
0033  . ISEQV    8   9
0034  . JMP      8 => 0042
0035  . UGET     8   2      ; buffers
0036  . TGETV    8   8   7
0037  . UGET     9   2      ; buffers
0038  . TGETV    9   9   7
0039  . LEN      9   9
0040  . ADDVN    9   9   0  ; 1
0041  . TSETV    3   8   9
0042  . FORL     4 => 0030
0043  . KPRI     4   2
0044  . MOV      5   3
0045  . RET      4   3
0019  ISNEP    8   0
0020  JMP     10 => 0022
0022  MOV      3   8
0023  ADDVV    7   7   9
0024  JMP      8 => 0014
0014  JLOOP    8   3
---- TRACE 9 IR
....        SNAP   #0   [ ---- ---- ---- ---- ---- ---- ---- ---- ---- ---- ]
0001 >  [1mfun[m SLOAD  #3    T
0002 >  [31mtab[m SLOAD  #4    T
0003 >  tru SLOAD  #5    T
0004 >  [1mfun[m EQ     0001  [1mtriplet_old.lua:572[m
0005    [35mint[m FLOAD  0002  tab.hmask
0006 >  [35mint[m EQ     0005  [35m+1  [m
0007    p64 FLOAD  0002  tab.node
0008 >  p64 HREFK  0007  [32m"buf"[m @1
0009 >  [31mtab[m HLOAD  0008
0010    [31mtab[m FLOAD  0009  tab.meta
0011 >  [31mtab[m EQ     0010  [31mNULL[m
0012    [35mint[m ALEN   0009  nil 
....        SNAP   #1   [ ---- ---- ---- ---- ---- true ---- ---- ---- ---- [1mtriplet_old.lua:572[m [34mftsz[m|[31m0002[m ---- ]
0013 >  [35mint[m LE     0012  [35m+0  [m
....        SNAP   #2   [ ---- ---- ---- ---- ---- true ---- ---- ---- ---- [1mtriplet_old.lua:572[m [34mftsz[m|[31m0002[m true ]
0014    p64 UREFC  [1mtriplet_old.lua:572[m  #0  
0015 >  [31mtab[m ULOAD  0014
0016    [35mint[m FLOAD  0015  tab.hmask
0017 >  [35mint[m EQ     0016  [35m+3  [m
0018    p64 FLOAD  0015  tab.node
0019 >  p64 HREFK  0018  [32m"g" [m @3
0020 >  [1mfun[m HLOAD  0019
0021 >  p64 HREFK  0018  [32m"p" [m @0
0022 >  [31mtab[m HLOAD  0021
0023 >  p64 HREFK  0018  [32m"c" [m @1
0024 >  [34mnum[m HLOAD  0023
0025 >  [1mfun[m EQ     0020  [1mtriplet_old.lua:33[m
0026    [34mnum[m ADD    0024  [34m+1  [m
0027    [31mtab[m FLOAD  0022  tab.meta
0028 >  [31mtab[m EQ     0027  [31mNULL[m
0029    [35mint[m ALEN   0022  nil 
0030    [34mnum[m CONV   0029  [34mnum[m.[35mint[m
....        SNAP   #3   [ ---- ---- ---- ---- ---- true ---- ---- ---- ---- [1mtriplet_old.lua:572[m [34mftsz[m|[31m0002[m true [1mtriplet_old.lua:33[m [34mftsz[m|---- ---- ]
0031 >  [34mnum[m UGE    0030  0026
....        SNAP   #4   [ ---- ---- ---- ---- ---- true ---- ---- ---- ---- [1mtriplet_old.lua:572[m [34mftsz[m|[31m0002[m true [1mtriplet_old.lua:33[m [34mftsz[m|[31m0022[m [34m0026[m ]
0032 >  [35mint[m CONV   0024  [35mint[m.[34mnum[m index
0033    [35mint[m ADD    0032  [35m+1  [m
0034    [35mint[m FLOAD  0022  tab.asize
0035 >  [35mint[m ABC    0034  0033
0036    p64 FLOAD  0022  tab.array
0037    p64 AREF   0036  0033
0038 >  [34mnum[m ALOAD  0037
0039    [34mnum[m HSTORE 0023  0026
....        SNAP   #5   [ ---- ---- ---- ---- ---- true ---- ---- ---- ---- [1mtriplet_old.lua:572[m [34mftsz[m|[31m0002[m true [34m0026[m [34m0038[m [35m+1  [m [35m+2  [m [35m+1  [m [35m+1  [m ]
0040    p64 UREFC  [1mtriplet_old.lua:572[m  #2  
0041 >  [31mtab[m ULOAD  0040
0042    [35mint[m FLOAD  0041  tab.asize
0043 >  [35mint[m ABC    0042  [35m+2  [m
0044    p64 FLOAD  0041  tab.array
0045    p64 AREF   0044  [35m+1  [m
0046 >  [31mtab[m ALOAD  0045
....        SNAP   #6   [ ---- ---- ---- ---- ---- true ---- ---- ---- ---- [1mtriplet_old.lua:572[m [34mftsz[m|[31m0002[m true [34m0026[m [34m0038[m [35m+1  [m [35m+2  [m [35m+1  [m [35m+1  [m [31m0046[m [31m0009[m ]
0047 >  [31mtab[m EQ     0046  0009
....        SNAP   #7   [ ---- ---- ---- ---- ---- true ---- ---- ---- ---- [1mtriplet_old.lua:572[m [34mftsz[m|[31m0002[m true [34m0026[m [34m0038[m [35m+2  [m [35m+2  [m [35m+1  [m [35m+2  [m ]
0048    p64 AREF   0044  [35m+2  [m
0049 >  [31mtab[m ALOAD  0048
....        SNAP   #8   [ ---- ---- ---- ---- ---- true ---- ---- ---- ---- [1mtriplet_old.lua:572[m [34mftsz[m|[31m0002[m true [34m0026[m [34m0038[m [35m+2  [m [35m+2  [m [35m+1  [m [35m+2  [m [31m0049[m [31m0009[m ]
0050 >  [31mtab[m NE     0049  0009
0051    [31mtab[m FLOAD  0049  tab.meta
0052 >  [31mtab[m EQ     0051  [31mNULL[m
0053    [35mint[m ALEN   0049  nil 
0054 >  [35mint[m ADDOV  0053  [35m+1  [m
0055    [35mint[m ADD    0053  [35m+1  [m
0056    [35mint[m FLOAD  0049  tab.asize
0057 >  [35mint[m ULE    0056  0055
0058    [35mint[m FLOAD  0049  tab.hmask
0059 >  [35mint[m EQ     0058  [35m+0  [m
0060    [34mnum[m CONV   0054  [34mnum[m.[35mint[m
0061    p64 NEWREF 0049  0060
0062    [34mnum[m HSTORE 0061  0038
....        SNAP   #9   [ ---- ---- ---- ---- ---- true ---- ---- ---- ---- [1mtriplet_old.lua:572[m [34mftsz[m|---- ---- ---- [34m0038[m ]
0063 >  [34mnum[m SLOAD  #9    T
0064  + [34mnum[m ADD    0063  0038
....        SNAP   #10  [ ---- ---- ---- ---- ---- true ---- ---- ---- [34m0064[m ]
0065 ------ LOOP ------------
0066    [35mint[m FLOAD  0002  tab.hmask
0067 >  [35mint[m EQ     0066  [35m+1  [m
0068    p64 FLOAD  0002  tab.node
0069 >  p64 HREFK  0068  [32m"buf"[m @1
0070 >  [31mtab[m HLOAD  0069
0071    [31mtab[m FLOAD  0070  tab.meta
0072 >  [31mtab[m EQ     0071  [31mNULL[m
0073    [35mint[m ALEN   0070  nil 
....        SNAP   #11  [ ---- ---- ---- ---- ---- true ---- ---- ---- [34m0064[m [1mtriplet_old.lua:572[m [34mftsz[m|[31m0002[m ---- ]
0074 >  [35mint[m LE     0073  [35m+0  [m
....        SNAP   #12  [ ---- ---- ---- ---- ---- true ---- ---- ---- [34m0064[m [1mtriplet_old.lua:572[m [34mftsz[m|[31m0002[m true ]
0075    [35mint[m FLOAD  0015  tab.hmask
0076 >  [35mint[m EQ     0075  [35m+3  [m
0077    p64 FLOAD  0015  tab.node
0078 >  p64 HREFK  0077  [32m"g" [m @3
0079 >  [1mfun[m HLOAD  0078
0080 >  p64 HREFK  0077  [32m"p" [m @0
0081 >  [31mtab[m HLOAD  0080
0082 >  p64 HREFK  0077  [32m"c" [m @1
0083 >  [34mnum[m HLOAD  0082
0084 >  [1mfun[m EQ     0079  [1mtriplet_old.lua:33[m
0085    [34mnum[m ADD    0083  [34m+1  [m
0086    [31mtab[m FLOAD  0081  tab.meta
0087 >  [31mtab[m EQ     0086  [31mNULL[m
0088    [35mint[m ALEN   0081  nil 
0089    [34mnum[m CONV   0088  [34mnum[m.[35mint[m
....        SNAP   #13  [ ---- ---- ---- ---- ---- true ---- ---- ---- [34m0064[m [1mtriplet_old.lua:572[m [34mftsz[m|[31m0002[m true [1mtriplet_old.lua:33[m [34mftsz[m|---- ---- ]
0090 >  [34mnum[m UGE    0089  0085
....        SNAP   #14  [ ---- ---- ---- ---- ---- true ---- ---- ---- [34m0064[m [1mtriplet_old.lua:572[m [34mftsz[m|[31m0002[m true [1mtriplet_old.lua:33[m [34mftsz[m|[31m0081[m [34m0085[m ]
0091 >  [35mint[m CONV   0083  [35mint[m.[34mnum[m index
0092    [35mint[m ADD    0091  [35m+1  [m
0093    [35mint[m FLOAD  0081  tab.asize
0094 >  [35mint[m ABC    0093  0092
0095    p64 FLOAD  0081  tab.array
0096    p64 AREF   0095  0092
0097 >  [34mnum[m ALOAD  0096
0098    [34mnum[m HSTORE 0082  0085
....        SNAP   #15  [ ---- ---- ---- ---- ---- true ---- ---- ---- [34m0064[m [1mtriplet_old.lua:572[m [34mftsz[m|[31m0002[m true [34m0085[m [34m0097[m [35m+1  [m [35m+2  [m [35m+1  [m [35m+1  [m ]
0099    [35mint[m FLOAD  0041  tab.asize
0100 >  [35mint[m ABC    0099  [35m+2  [m
0101    p64 FLOAD  0041  tab.array
0102    p64 AREF   0101  [35m+1  [m
0103 >  [31mtab[m ALOAD  0102
....        SNAP   #16  [ ---- ---- ---- ---- ---- true ---- ---- ---- [34m0064[m [1mtriplet_old.lua:572[m [34mftsz[m|[31m0002[m true [34m0085[m [34m0097[m [35m+1  [m [35m+2  [m [35m+1  [m [35m+1  [m [31m0103[m [31m0070[m ]
0104 >  [31mtab[m EQ     0103  0070
....        SNAP   #17  [ ---- ---- ---- ---- ---- true ---- ---- ---- [34m0064[m [1mtriplet_old.lua:572[m [34mftsz[m|[31m0002[m true [34m0085[m [34m0097[m [35m+2  [m [35m+2  [m [35m+1  [m [35m+2  [m ]
0105    p64 AREF   0101  [35m+2  [m
0106 >  [31mtab[m ALOAD  0105
....        SNAP   #18  [ ---- ---- ---- ---- ---- true ---- ---- ---- [34m0064[m [1mtriplet_old.lua:572[m [34mftsz[m|[31m0002[m true [34m0085[m [34m0097[m [35m+2  [m [35m+2  [m [35m+1  [m [35m+2  [m [31m0106[m [31m0070[m ]
0107 >  [31mtab[m NE     0106  0070
0108    [31mtab[m FLOAD  0106  tab.meta
0109 >  [31mtab[m EQ     0108  [31mNULL[m
0110    [35mint[m ALEN   0106  nil 
0111 >  [35mint[m ADDOV  0110  [35m+1  [m
0112    [35mint[m ADD    0110  [35m+1  [m
0113    [35mint[m FLOAD  0106  tab.asize
0114 >  [35mint[m ULE    0113  0112
0115    [35mint[m FLOAD  0106  tab.hmask
0116 >  [35mint[m EQ     0115  [35m+0  [m
0117    [34mnum[m CONV   0111  [34mnum[m.[35mint[m
0118    p64 NEWREF 0106  0117
0119    [34mnum[m HSTORE 0118  0097
0120  + [34mnum[m ADD    0097  0064
0121    [34mnum[m PHI    0064  0120
---- TRACE 9 stop -> loop

---- TRACE 10 start 9/8 triplet_old.lua:581
0033  . ISEQV    8   9
0034  . JMP      8 => 0042
0035  . UGET     8   2      ; buffers
0036  . TGETV    8   8   7
0037  . UGET     9   2      ; buffers
0038  . TGETV    9   9   7
0039  . LEN      9   9
0040  . ADDVN    9   9   0  ; 1
0041  . TSETV    3   8   9
0042  . FORL     4 => 0030
0043  . KPRI     4   2
0044  . MOV      5   3
0045  . RET      4   3
0019  ISNEP    8   0
0020  JMP     10 => 0022
0022  MOV      3   8
0023  ADDVV    7   7   9
0024  JMP      8 => 0014
0014  JLOOP    8   3
---- TRACE 10 IR
0001    [31mtab[m SLOAD  #12   PI
0002    [34mnum[m SLOAD  #14   PI
0003    [34mnum[m SLOAD  #15   PI
0004    [31mtab[m SLOAD  #20   PI
0005    [31mtab[m SLOAD  #21   PI
....        SNAP   #0   [ ---- ---- ---- ---- ---- true ---- ---- ---- ---- [1mtriplet_old.lua:572[m [34mftsz[m|[31m0001[m true [34m0002[m [34m0003[m [35m+2  [m [35m+2  [m [35m+1  [m [35m+2  [m [31m0004[m [31m0005[m ]
....        SNAP   #1   [ ---- ---- ---- ---- ---- true ---- ---- ---- ---- [1mtriplet_old.lua:572[m [34mftsz[m|[31m0001[m true [34m0002[m [34m0003[m [35m+2  [m [35m+2  [m [35m+1  [m [35m+2  [m [31m0004[m [31m0005[m ]
0007 >  [31mtab[m NE     0005  0004
0008    [31mtab[m FLOAD  0004  tab.meta
0009 >  [31mtab[m EQ     0008  [31mNULL[m
0010    p64 UREFC  [1mtriplet_old.lua:572[m  #2  
0011 >  [31mtab[m ULOAD  0010
0012    [35mint[m FLOAD  0011  tab.asize
0013 >  [35mint[m ABC    0012  [35m+2  [m
0014    p64 FLOAD  0011  tab.array
0015    p64 AREF   0014  [35m+2  [m
0016 >  [31mtab[m ALOAD  0015
0017    [31mtab[m FLOAD  0016  tab.meta
0018 >  [31mtab[m EQ     0017  [31mNULL[m
0019    [35mint[m ALEN   0016  nil 
0020 >  [35mint[m ADDOV  0019  [35m+1  [m
0021    [35mint[m ADD    0019  [35m+1  [m
0022    [35mint[m FLOAD  0016  tab.asize
0023 >  [35mint[m ABC    0022  0021
0024    p64 FLOAD  0016  tab.array
0025    p64 AREF   0024  0021
0026    [34mnum[m ASTORE 0025  0003
....        SNAP   #2   [ ---- ---- ---- ---- ---- true ---- ---- ---- ---- [1mtriplet_old.lua:572[m [34mftsz[m|---- ---- ---- [34m0003[m ]
0027 >  [34mnum[m SLOAD  #9    T
0028    [34mnum[m ADD    0027  0003
....        SNAP   #3   [ ---- ---- ---- ---- ---- true ---- ---- ---- [34m0028[m ]
---- TRACE 10 stop -> 3

---- TRACE 11 start 9/18 triplet_old.lua:581
0033  . ISEQV    8   9
0034  . JMP      8 => 0042
0035  . UGET     8   2      ; buffers
0036  . TGETV    8   8   7
0037  . UGET     9   2      ; buffers
0038  . TGETV    9   9   7
0039  . LEN      9   9
0040  . ADDVN    9   9   0  ; 1
0041  . TSETV    3   8   9
0042  . FORL     4 => 0030
0043  . KPRI     4   2
0044  . MOV      5   3
0045  . RET      4   3
0019  ISNEP    8   0
0020  JMP     10 => 0022
0022  MOV      3   8
0023  ADDVV    7   7   9
0024  JMP      8 => 0014
0014  JLOOP    8   3
---- TRACE 11 IR
0001    [34mnum[m SLOAD  #9    PI
0002    [31mtab[m SLOAD  #12   PI
0003    [34mnum[m SLOAD  #14   PI
0004    [34mnum[m SLOAD  #15   PI
0005    [31mtab[m SLOAD  #20   PI
0006    [31mtab[m SLOAD  #21   PI
....        SNAP   #0   [ ---- ---- ---- ---- ---- true ---- ---- ---- [34m0001[m [1mtriplet_old.lua:572[m [34mftsz[m|[31m0002[m true [34m0003[m [34m0004[m [35m+2  [m [35m+2  [m [35m+1  [m [35m+2  [m [31m0005[m [31m0006[m ]
....        SNAP   #1   [ ---- ---- ---- ---- ---- true ---- ---- ---- [34m0001[m [1mtriplet_old.lua:572[m [34mftsz[m|[31m0002[m true [34m0003[m [34m0004[m [35m+2  [m [35m+2  [m [35m+1  [m [35m+2  [m [31m0005[m [31m0006[m ]
0008 >  [31mtab[m NE     0006  0005
0009    [31mtab[m FLOAD  0005  tab.meta
0010 >  [31mtab[m EQ     0009  [31mNULL[m
0011    p64 UREFC  [1mtriplet_old.lua:572[m  #2  
0012 >  [31mtab[m ULOAD  0011
0013    [35mint[m FLOAD  0012  tab.asize
0014 >  [35mint[m ABC    0013  [35m+2  [m
0015    p64 FLOAD  0012  tab.array
0016    p64 AREF   0015  [35m+2  [m
0017 >  [31mtab[m ALOAD  0016
0018    [31mtab[m FLOAD  0017  tab.meta
0019 >  [31mtab[m EQ     0018  [31mNULL[m
0020    [35mint[m ALEN   0017  nil 
0021 >  [35mint[m ADDOV  0020  [35m+1  [m
0022    [35mint[m ADD    0020  [35m+1  [m
0023    [35mint[m FLOAD  0017  tab.asize
0024 >  [35mint[m ABC    0023  0022
0025    p64 FLOAD  0017  tab.array
0026    p64 AREF   0025  0022
0027    [34mnum[m ASTORE 0026  0004
0028    [34mnum[m ADD    0004  0001
....        SNAP   #2   [ ---- ---- ---- ---- ---- true ---- ---- ---- [34m0028[m ]
---- TRACE 11 stop -> 3

---- TRACE 12 start 9/3 triplet_old.lua:35
0005  . . KPRI     2   0
0006  . . RET1     2   2
0020  . ISNEP    2   0
0021  . JMP      4 => 0024
0022  . KPRI     4   0
0023  . RET1     4   2
0019  ISNEP    8   0
0020  JMP     10 => 0022
0021  JMP      8 => 0025
0025  LOOP     8 => 0036
0026  MOV      8   4
0027  MOV     10   5
0028  MOV     11   6
0029  CALL     8   3   3
0000  . FUNCF   10          ; triplet_old.lua:572
0001  . TGETS    2   0   0  ; "buf"
0002  . LEN      2   2
0003  . KSHORT   3   0
0004  . ISGE     3   2
0005  . JMP      2 => 0013
0006  . KPRI     2   2
0007  . GGET     3   1      ; "table"
0008  . TGETS    3   3   2  ; "remove"
0009  . TGETS    5   0   0  ; "buf"
0010  . KSHORT   6   1
0011  . CALL     3   0   3
0000  . . FUNCF   10          ; builtin:remove
0001  . . ISTYPE   0  12
0002  . . LEN      2   0
0003  . . ISNEP    1   0
0004  . . JMP      3 => 0012
0012  . . ISNUM    1  15
0013  . . KSHORT   3   1
0014  . . ISGT     3   1
0015  . . JMP      3 => 0030
0016  . . ISGT     1   2
0017  . . JMP      3 => 0030
0018  . . TGETR    3   0   1
0019  . . ADDVN    4   1   1  ; 1
0020  . . MOV      5   2
0021  . . KSHORT   6   1
0022  . . JFORI    4 => 0027
---- TRACE 12 IR
0001    [31mtab[m SLOAD  #12   PI
....        SNAP   #0   [ ---- ---- ---- ---- ---- true ---- ---- ---- ---- [1mtriplet_old.lua:572[m [34mftsz[m|[31m0001[m true [1mtriplet_old.lua:33[m [34mftsz[m|---- ---- ]
0002 >  [1mfun[m SLOAD  #6    T
0003 >  [31mtab[m SLOAD  #7    T
0004 >  tru SLOAD  #8    T
0005 >  [1mfun[m EQ     0002  [1mtriplet_old.lua:572[m
0006    [35mint[m FLOAD  0003  tab.hmask
0007 >  [35mint[m EQ     0006  [35m+1  [m
0008    p64 FLOAD  0003  tab.node
0009 >  p64 HREFK  0008  [32m"buf"[m @1
0010 >  [31mtab[m HLOAD  0009
0011    [31mtab[m FLOAD  0010  tab.meta
0012 >  [31mtab[m EQ     0011  [31mNULL[m
0013    [35mint[m ALEN   0010  nil 
....        SNAP   #1   [ ---- ---- ---- ---- ---- true ---- ---- true ---- [1mtriplet_old.lua:572[m [34mftsz[m|[31m0003[m true ]
0014 >  [35mint[m GT     0013  [35m+0  [m
....        SNAP   #2   [ ---- ---- ---- ---- ---- true ---- ---- true ---- [1mtriplet_old.lua:572[m [34mftsz[m|[31m0003[m ---- ]
0015    [31mtab[m FLOAD  [1mtriplet_old.lua:572[m  func.env
0016    [35mint[m FLOAD  0015  tab.hmask
0017 >  [35mint[m EQ     0016  [35m+63 [m
0018    p64 FLOAD  0015  tab.node
0019 >  p64 HREFK  0018  [32m"table"[m @14
0020 >  [31mtab[m HLOAD  0019
0021    [35mint[m FLOAD  0020  tab.hmask
0022 >  [35mint[m EQ     0021  [35m+15 [m
0023    p64 FLOAD  0020  tab.node
0024 >  p64 HREFK  0023  [32m"remove"[m @12
0025 >  [1mfun[m HLOAD  0024
0026 >  [1mfun[m EQ     0025  [1mbuiltin:remove[m
0027    [34mnum[m CONV   0013  [34mnum[m.[35mint[m
....        SNAP   #3   [ ---- ---- ---- ---- ---- true ---- ---- true ---- [1mtriplet_old.lua:572[m [34mftsz[m|[31m0003[m ---- true [1mbuiltin:remove[m [34mftsz[m|---- ---- ---- ]
0028 >  [34mnum[m GE     0027  [34m+1  [m
....        SNAP   #4   [ ---- ---- ---- ---- ---- true ---- ---- true ---- [1mtriplet_old.lua:572[m [34mftsz[m|[31m0003[m ---- true [1mbuiltin:remove[m [34mftsz[m|[31m0010[m [34m+1  [m [35m0013[m ]
0029    [35mint[m FLOAD  0010  tab.asize
0030 >  [35mint[m ABC    0029  [35m+1  [m
0031    p64 FLOAD  0010  tab.array
0032    p64 AREF   0031  [35m+1  [m
0033 >  [34mnum[m ALOAD  0032
....        SNAP   #5   [ ---- ---- ---- ---- ---- true ---- ---- true ---- [1mtriplet_old.lua:572[m [34mftsz[m|[31m0003[m ---- true [1mbuiltin:remove[m [34mftsz[m|[31m0010[m [34m+1  [m [35m0013[m [34m0033[m ]
0034 >  [34mnum[m GE     0027  [34m+2  [m
....        SNAP   #6   [ ---- ---- ---- ---- ---- true ---- ---- true ---- [1mtriplet_old.lua:572[m [34mftsz[m|[31m0003[m ---- true [1mbuiltin:remove[m [34mftsz[m|[31m0010[m [34m+1  [m [34m0027[m [34m0033[m [34m+2  [m [34m0027[m [34m+1  [m [34m+2  [m ]
---- TRACE 12 stop -> 5

---- TRACE 13 start 6/5 triplet_bench_lib.lua:149
0030  ISNEP    8   0
0031  JMP     10 => 0033
0033  MOV      6   8
0034  ADDVV    7   7   9
0035  JMP      8 => 0025
0025  LOOP     8 => 0036
0026  MOV      8   4
0027  MOV     10   5
0028  MOV     11   6
0029  CALL     8   3   3
0000  . FUNCF   10          ; triplet_old.lua:572
0001  . TGETS    2   0   0  ; "buf"
0002  . LEN      2   2
0003  . KSHORT   3   0
0004  . ISGE     3   2
0005  . JMP      2 => 0013
0006  . KPRI     2   2
0007  . GGET     3   1      ; "table"
0008  . TGETS    3   3   2  ; "remove"
0009  . TGETS    5   0   0  ; "buf"
0010  . KSHORT   6   1
0011  . CALL     3   0   3
0000  . . FUNCF   10          ; builtin:remove
0001  . . ISTYPE   0  12
0002  . . LEN      2   0
0003  . . ISNEP    1   0
0004  . . JMP      3 => 0012
0012  . . ISNUM    1  15
0013  . . KSHORT   3   1
0014  . . ISGT     3   1
0015  . . JMP      3 => 0030
0016  . . ISGT     1   2
0017  . . JMP      3 => 0030
0018  . . TGETR    3   0   1
0019  . . ADDVN    4   1   1  ; 1
0020  . . MOV      5   2
0021  . . KSHORT   6   1
0022  . . JFORI    4 => 0027
---- TRACE 13 IR
0001    [34mnum[m SLOAD  #11   PI
....        SNAP   #0   [ ---- ---- ---- ---- ---- ---- ---- ---- ---- ---- true [34m0001[m ]
0002 >  [34mnum[m SLOAD  #9    T
0003    [34mnum[m ADD    0002  0001
0004 >  [1mfun[m SLOAD  #6    T
0005 >  [31mtab[m SLOAD  #7    T
0006 >  [1mfun[m EQ     0004  [1mtriplet_old.lua:572[m
0007    [35mint[m FLOAD  0005  tab.hmask
0008 >  [35mint[m EQ     0007  [35m+1  [m
0009    p64 FLOAD  0005  tab.node
0010 >  p64 HREFK  0009  [32m"buf"[m @1
0011 >  [31mtab[m HLOAD  0010
0012    [31mtab[m FLOAD  0011  tab.meta
0013 >  [31mtab[m EQ     0012  [31mNULL[m
0014    [35mint[m ALEN   0011  nil 
....        SNAP   #1   [ ---- ---- ---- ---- ---- ---- ---- ---- true [34m0003[m [1mtriplet_old.lua:572[m [34mftsz[m|[31m0005[m true ]
0015 >  [35mint[m GT     0014  [35m+0  [m
....        SNAP   #2   [ ---- ---- ---- ---- ---- ---- ---- ---- true [34m0003[m [1mtriplet_old.lua:572[m [34mftsz[m|[31m0005[m ---- ]
0016    [31mtab[m FLOAD  [1mtriplet_old.lua:572[m  func.env
0017    [35mint[m FLOAD  0016  tab.hmask
0018 >  [35mint[m EQ     0017  [35m+63 [m
0019    p64 FLOAD  0016  tab.node
0020 >  p64 HREFK  0019  [32m"table"[m @14
0021 >  [31mtab[m HLOAD  0020
0022    [35mint[m FLOAD  0021  tab.hmask
0023 >  [35mint[m EQ     0022  [35m+15 [m
0024    p64 FLOAD  0021  tab.node
0025 >  p64 HREFK  0024  [32m"remove"[m @12
0026 >  [1mfun[m HLOAD  0025
0027 >  [1mfun[m EQ     0026  [1mbuiltin:remove[m
0028    [34mnum[m CONV   0014  [34mnum[m.[35mint[m
....        SNAP   #3   [ ---- ---- ---- ---- ---- ---- ---- ---- true [34m0003[m [1mtriplet_old.lua:572[m [34mftsz[m|[31m0005[m ---- true [1mbuiltin:remove[m [34mftsz[m|---- ---- ---- ]
0029 >  [34mnum[m GE     0028  [34m+1  [m
....        SNAP   #4   [ ---- ---- ---- ---- ---- ---- ---- ---- true [34m0003[m [1mtriplet_old.lua:572[m [34mftsz[m|[31m0005[m ---- true [1mbuiltin:remove[m [34mftsz[m|[31m0011[m [34m+1  [m [35m0014[m ]
0030    [35mint[m FLOAD  0011  tab.asize
0031 >  [35mint[m ABC    0030  [35m+1  [m
0032    p64 FLOAD  0011  tab.array
0033    p64 AREF   0032  [35m+1  [m
0034 >  [34mnum[m ALOAD  0033
....        SNAP   #5   [ ---- ---- ---- ---- ---- ---- ---- ---- true [34m0003[m [1mtriplet_old.lua:572[m [34mftsz[m|[31m0005[m ---- true [1mbuiltin:remove[m [34mftsz[m|[31m0011[m [34m+1  [m [35m0014[m [34m0034[m ]
0035 >  [34mnum[m GE     0028  [34m+2  [m
....        SNAP   #6   [ ---- ---- ---- ---- ---- ---- ---- ---- true [34m0003[m [1mtriplet_old.lua:572[m [34mftsz[m|[31m0005[m ---- true [1mbuiltin:remove[m [34mftsz[m|[31m0011[m [34m+1  [m [34m0028[m [34m0034[m [34m+2  [m [34m0028[m [34m+1  [m [34m+2  [m ]
---- TRACE 13 stop -> 5

---- TRACE 14 start 5/1 builtin:remove
0027  KPRI     4   0
0028  TSETR    4   0   2
0029  RET1     3   2
0012  RETM     2   1
0030  ISNEP    8   0
0031  JMP     10 => 0033
0033  MOV      6   8
0034  ADDVV    7   7   9
0035  JMP      8 => 0025
0025  LOOP     8 => 0036
0026  MOV      8   4
0027  MOV     10   5
0028  MOV     11   6
0029  CALL     8   3   3
0000  . FUNCF   10          ; triplet_old.lua:572
0001  . TGETS    2   0   0  ; "buf"
0002  . LEN      2   2
0003  . KSHORT   3   0
0004  . ISGE     3   2
0005  . JMP      2 => 0013
0006  . KPRI     2   2
0007  . GGET     3   1      ; "table"
0008  . TGETS    3   3   2  ; "remove"
0009  . TGETS    5   0   0  ; "buf"
0010  . KSHORT   6   1
0011  . CALL     3   0   3
0000  . . FUNCF   10          ; builtin:remove
0001  . . ISTYPE   0  12
0002  . . LEN      2   0
0003  . . ISNEP    1   0
0004  . . JMP      3 => 0012
0012  . . ISNUM    1  15
0013  . . KSHORT   3   1
0014  . . ISGT     3   1
0015  . . JMP      3 => 0030
0016  . . ISGT     1   2
0017  . . JMP      3 => 0030
0018  . . TGETR    3   0   1
0019  . . ADDVN    4   1   1  ; 1
0020  . . MOV      5   2
0021  . . KSHORT   6   1
0022  . . JFORI    4 => 0027
0027  . . KPRI     4   0
0028  . . TSETR    4   0   2
0029  . . RET1     3   2
0012  . RETM     2   1
0030  ISNEP    8   0
0031  JMP     10 => 0033
0033  MOV      6   8
0034  ADDVV    7   7   9
0035  JMP      8 => 0025
0025  LOOP     8 => 0036
0026  MOV      8   4
0027  MOV     10   5
0028  MOV     11   6
0029  CALL     8   3   3
0000  . FUNCF   10          ; triplet_old.lua:572
0001  . TGETS    2   0   0  ; "buf"
0002  . LEN      2   2
0003  . KSHORT   3   0
0004  . ISGE     3   2
0005  . JMP      2 => 0013
0013  . UGET     2   0      ; state
0014  . TGETS    2   2   3  ; "g"
0015  . UGET     4   0      ; state
0016  . TGETS    4   4   4  ; "p"
0017  . UGET     5   0      ; state
0018  . TGETS    5   5   5  ; "c"
0019  . CALL     2   3   3
0000  . . FUNCF    4          ; triplet_old.lua:33
0001  . . ADDVN    1   1   0  ; 1
0002  . . LEN      2   0
0003  . . ISGE     2   1
0004  . . JMP      2 => 0007
0005  . . KPRI     2   0
0006  . . RET1     2   2
0020  . ISNEP    2   0
0021  . JMP      4 => 0024
0022  . KPRI     4   0
0023  . RET1     4   2
0030  ISNEP    8   0
0031  JMP     10 => 0033
0032  JMP      8 => 0036
0036  RET1     7   2
0099  ADDVV   13  13  18
0100  FORL    14 => 0097
0097  MOV     18  12
0098  CALL    18   2   1
0000  . FUNCF    5          ; triplet_trace.lua:19
0001  . UGET     0   0      ; lib
0002  . TGETS    0   0   0  ; "run_once"
0003  . UGET     2   1      ; T
0004  . UGET     3   2      ; scenario_name
0005  . UGET     4   3      ; payload
0006  . CALLT    0   4
0000  . FUNCF    7          ; triplet_bench_lib.lua:426
0001  . UGET     3   0      ; M
0002  . TGETS    3   3   0  ; "get_scenario"
0003  . MOV      5   1
0004  . CALL     3   2   2
0000  . . FUNCF    8          ; triplet_bench_lib.lua:413
0001  . . UGET     1   0      ; scenarios
0002  . . TGETV    1   1   0
0003  . . IST          1
0004  . . JMP      2 => 0013
0013  . . RET1     1   2
0005  . TGETS    3   3   1  ; "run_once"
0006  . MOV      5   0
0007  . MOV      6   2
0008  . CALLT    3   3
0000  . FUNCF    8          ; triplet_bench_lib.lua:358
0001  . TGETS    2   0   0  ; "tee"
0002  . KSHORT   4   2
0003  . TGETS    5   0   1  ; "seq"
0004  . TGETS    7   1   2  ; "values"
0005  . CALL     5   0   2
0000  . . FUNCF    4          ; triplet_old.lua:32
0001  . . FNEW     1   0      ; triplet_old.lua:33
---- TRACE 14 abort triplet_old.lua:37 -- NYI: bytecode FNEW  

---- TRACE 14 start triplet_old.lua:567
0001  TNEW     4   0
0002  TDUP     5   0
0003  TSETS    1   5   1  ; "g"
0004  TSETS    2   5   2  ; "p"
0005  TSETS    3   5   3  ; "c"
0006  KSHORT   6   1
0007  MOV      7   0
0008  KSHORT   8   1
0009  FORI     6 => 0013
0010  TNEW    10   0
0011  TSETV   10   4   9
0012  FORL     6 => 0010
---- TRACE 14 abort triplet_old.lua:570 -- inner loop in root trace

---- TRACE 14 start 9/0 triplet_bench_lib.lua:139
0015  MOV      8   1
0016  MOV     10   2
0017  MOV     11   3
0018  CALL     8   3   3
0000  . FUNCF   10          ; triplet_old.lua:572
0001  . TGETS    2   0   0  ; "buf"
0002  . LEN      2   2
0003  . KSHORT   3   0
0004  . ISGE     3   2
0005  . JMP      2 => 0013
0013  . UGET     2   0      ; state
0014  . TGETS    2   2   3  ; "g"
0015  . UGET     4   0      ; state
0016  . TGETS    4   4   4  ; "p"
0017  . UGET     5   0      ; state
0018  . TGETS    5   5   5  ; "c"
0019  . CALL     2   3   3
0000  . . FUNCF    4          ; triplet_old.lua:33
0001  . . ADDVN    1   1   0  ; 1
0002  . . LEN      2   0
0003  . . ISGE     2   1
0004  . . JMP      2 => 0007
0007  . . MOV      2   1
0008  . . TGETV    3   0   1
0009  . . RET      2   3
0020  . ISNEP    2   0
0021  . JMP      4 => 0024
0024  . UGET     4   0      ; state
0025  . TSETS    2   4   5  ; "c"
0026  . KSHORT   4   1
0027  . UGET     5   1      ; n
0028  . KSHORT   6   1
0029  . FORI     4 => 0043
0030  . UGET     8   2      ; buffers
0031  . TGETV    8   8   7
0032  . TGETS    9   0   0  ; "buf"
0033  . ISEQV    8   9
0034  . JMP      8 => 0042
0042  . FORL     4 => 0030
0030  . UGET     8   2      ; buffers
0031  . TGETV    8   8   7
0032  . TGETS    9   0   0  ; "buf"
0033  . ISEQV    8   9
0034  . JMP      8 => 0042
0035  . UGET     8   2      ; buffers
0036  . TGETV    8   8   7
0037  . UGET     9   2      ; buffers
0038  . TGETV    9   9   7
0039  . LEN      9   9
0040  . ADDVN    9   9   0  ; 1
0041  . TSETV    3   8   9
0042  . FORL     4 => 0030
0043  . KPRI     4   2
0044  . MOV      5   3
0045  . RET      4   3
0019  ISNEP    8   0
0020  JMP     10 => 0022
0022  MOV      3   8
0023  ADDVV    7   7   9
0024  JMP      8 => 0014
0014  JLOOP    8   3
---- TRACE 14 IR
....        SNAP   #0   [ ---- ---- ---- ---- ---- ---- ---- ---- ---- ---- ]
0001 >  [1mfun[m SLOAD  #3    T
0002 >  [31mtab[m SLOAD  #4    T
0003 >  tru SLOAD  #5    T
0004    p64 FLOAD  0001  func.pc
0005 >  p64 EQ     0004  [0x7f38e8111fc8]
0006    [35mint[m FLOAD  0002  tab.hmask
0007 >  [35mint[m EQ     0006  [35m+1  [m
0008    p64 FLOAD  0002  tab.node
0009 >  p64 HREFK  0008  [32m"buf"[m @1
0010 >  [31mtab[m HLOAD  0009
0011    [31mtab[m FLOAD  0010  tab.meta
0012 >  [31mtab[m EQ     0011  [31mNULL[m
0013    [35mint[m ALEN   0010  nil 
....        SNAP   #1   [ ---- ---- ---- ---- ---- true ---- ---- ---- ---- [1m0001[m [34mftsz[m|[31m0002[m ---- ]
0014 >  [35mint[m LE     0013  [35m+0  [m
....        SNAP   #2   [ ---- ---- ---- ---- ---- true ---- ---- ---- ---- [1m0001[m [34mftsz[m|[31m0002[m true ]
0015 >  p64 UREFC  0001  #0  
0016 >  [31mtab[m ULOAD  0015
0017    [35mint[m FLOAD  0016  tab.hmask
0018 >  [35mint[m EQ     0017  [35m+3  [m
0019    p64 FLOAD  0016  tab.node
0020 >  p64 HREFK  0019  [32m"g" [m @3
0021 >  [1mfun[m HLOAD  0020
0022 >  p64 HREFK  0019  [32m"p" [m @0
0023 >  [31mtab[m HLOAD  0022
0024 >  p64 HREFK  0019  [32m"c" [m @1
0025 >  [34mnum[m HLOAD  0024
0026    p64 FLOAD  0021  func.pc
0027 >  p64 EQ     0026  [0x7f38e80edfc0]
0028    [34mnum[m ADD    0025  [34m+1  [m
0029    [31mtab[m FLOAD  0023  tab.meta
0030 >  [31mtab[m EQ     0029  [31mNULL[m
0031    [35mint[m ALEN   0023  nil 
0032    [34mnum[m CONV   0031  [34mnum[m.[35mint[m
....        SNAP   #3   [ ---- ---- ---- ---- ---- true ---- ---- ---- ---- [1m0001[m [34mftsz[m|[31m0002[m true [1m0021[m [34mftsz[m|---- ---- ]
0033 >  [34mnum[m UGE    0032  0028
....        SNAP   #4   [ ---- ---- ---- ---- ---- true ---- ---- ---- ---- [1m0001[m [34mftsz[m|[31m0002[m true [1m0021[m [34mftsz[m|[31m0023[m [34m0028[m ]
0034 >  [35mint[m CONV   0025  [35mint[m.[34mnum[m index
0035    [35mint[m ADD    0034  [35m+1  [m
0036    [35mint[m FLOAD  0023  tab.asize
0037 >  [35mint[m ABC    0036  0035
0038    p64 FLOAD  0023  tab.array
0039    p64 AREF   0038  0035
0040 >  [34mnum[m ALOAD  0039
0041    [34mnum[m HSTORE 0024  0028
....        SNAP   #5   [ ---- ---- ---- ---- ---- true ---- ---- ---- ---- [1m0001[m [34mftsz[m|[31m0002[m true [34m0028[m [34m0040[m [31m0016[m ]
0042 >  p64 UREFC  0001  #1  
0043 >  [34mnum[m ULOAD  0042
0044 >  [35mint[m CONV   0043  [35mint[m.[34mnum[m check
0045 >  [35mint[m LE     0044  [35m+2147483646[m
....        SNAP   #6   [ ---- ---- ---- ---- ---- true ---- ---- ---- ---- [1m0001[m [34mftsz[m|[31m0002[m true [34m0028[m [34m0040[m ]
0046 >  [35mint[m GE     0044  [35m+1  [m
....        SNAP   #7   [ ---- ---- ---- ---- ---- true ---- ---- ---- ---- [1m0001[m [34mftsz[m|[31m0002[m true [34m0028[m [34m0040[m [35m+1  [m [35m0044[m [35m+1  [m [35m+1  [m ]
0047 >  p64 UREFC  0001  #2  
0048 >  [31mtab[m ULOAD  0047
0049    [35mint[m FLOAD  0048  tab.asize
0050 >  [35mint[m ABC    0049  [35m+2  [m
0051    p64 FLOAD  0048  tab.array
0052    p64 AREF   0051  [35m+1  [m
0053 >  [31mtab[m ALOAD  0052
....        SNAP   #8   [ ---- ---- ---- ---- ---- true ---- ---- ---- ---- [1m0001[m [34mftsz[m|[31m0002[m true [34m0028[m [34m0040[m [35m+1  [m [35m0044[m [35m+1  [m [35m+1  [m [31m0053[m [31m0010[m ]
0054 >  [31mtab[m EQ     0053  0010
....        SNAP   #9   [ ---- ---- ---- ---- ---- true ---- ---- ---- ---- [1m0001[m [34mftsz[m|[31m0002[m true [34m0028[m [34m0040[m ]
0055 >  [35mint[m GE     0044  [35m+2  [m
....        SNAP   #10  [ ---- ---- ---- ---- ---- true ---- ---- ---- ---- [1m0001[m [34mftsz[m|[31m0002[m true [34m0028[m [34m0040[m [35m+2  [m [35m0044[m [35m+1  [m [35m+2  [m ]
0056    p64 AREF   0051  [35m+2  [m
0057 >  [31mtab[m ALOAD  0056
....        SNAP   #11  [ ---- ---- ---- ---- ---- true ---- ---- ---- ---- [1m0001[m [34mftsz[m|[31m0002[m true [34m0028[m [34m0040[m [35m+2  [m [35m0044[m [35m+1  [m [35m+2  [m [31m0057[m [31m0010[m ]
0058 >  [31mtab[m NE     0057  0010
0059    [31mtab[m FLOAD  0057  tab.meta
0060 >  [31mtab[m EQ     0059  [31mNULL[m
0061    [35mint[m ALEN   0057  nil 
0062 >  [35mint[m ADDOV  0061  [35m+1  [m
0063    [35mint[m ADD    0061  [35m+1  [m
0064    [35mint[m FLOAD  0057  tab.asize
0065 >  [35mint[m ULE    0064  0063
0066    [35mint[m FLOAD  0057  tab.hmask
0067 >  [35mint[m EQ     0066  [35m+0  [m
0068    [34mnum[m CONV   0062  [34mnum[m.[35mint[m
0069    p64 NEWREF 0057  0068
0070    [34mnum[m HSTORE 0069  0040
....        SNAP   #12  [ ---- ---- ---- ---- ---- true ---- ---- ---- ---- [1m0001[m [34mftsz[m|[31m0002[m true [34m0028[m [34m0040[m [35m+3  [m [35m0044[m [35m+1  [m [35m+3  [m ]
0071 >  [35mint[m LT     0044  [35m+3  [m
....        SNAP   #13  [ ---- ---- ---- ---- ---- true ---- ---- ---- ---- [1m0001[m [34mftsz[m|---- ---- ---- [34m0040[m ]
0072 >  [34mnum[m SLOAD  #9    T
0073  + [34mnum[m ADD    0072  0040
....        SNAP   #14  [ ---- ---- ---- ---- ---- true ---- ---- ---- [34m0073[m ]
0074 ------ LOOP ------------
0075    [35mint[m FLOAD  0002  tab.hmask
0076 >  [35mint[m EQ     0075  [35m+1  [m
0077    p64 FLOAD  0002  tab.node
0078 >  p64 HREFK  0077  [32m"buf"[m @1
0079 >  [31mtab[m HLOAD  0078
0080    [31mtab[m FLOAD  0079  tab.meta
0081 >  [31mtab[m EQ     0080  [31mNULL[m
0082    [35mint[m ALEN   0079  nil 
....        SNAP   #15  [ ---- ---- ---- ---- ---- true ---- ---- ---- [34m0073[m [1m0001[m [34mftsz[m|[31m0002[m ---- ]
0083 >  [35mint[m LE     0082  [35m+0  [m
....        SNAP   #16  [ ---- ---- ---- ---- ---- true ---- ---- ---- [34m0073[m [1m0001[m [34mftsz[m|[31m0002[m true ]
0084    [35mint[m FLOAD  0016  tab.hmask
0085 >  [35mint[m EQ     0084  [35m+3  [m
0086    p64 FLOAD  0016  tab.node
0087 >  p64 HREFK  0086  [32m"g" [m @3
0088 >  [1mfun[m HLOAD  0087
0089 >  p64 HREFK  0086  [32m"p" [m @0
0090 >  [31mtab[m HLOAD  0089
0091 >  p64 HREFK  0086  [32m"c" [m @1
0092 >  [34mnum[m HLOAD  0091
0093    p64 FLOAD  0088  func.pc
0094 >  p64 EQ     0093  [0x7f38e80edfc0]
0095    [34mnum[m ADD    0092  [34m+1  [m
0096    [31mtab[m FLOAD  0090  tab.meta
0097 >  [31mtab[m EQ     0096  [31mNULL[m
0098    [35mint[m ALEN   0090  nil 
0099    [34mnum[m CONV   0098  [34mnum[m.[35mint[m
....        SNAP   #17  [ ---- ---- ---- ---- ---- true ---- ---- ---- [34m0073[m [1m0001[m [34mftsz[m|[31m0002[m true [1m0088[m [34mftsz[m|---- ---- ]
0100 >  [34mnum[m UGE    0099  0095
....        SNAP   #18  [ ---- ---- ---- ---- ---- true ---- ---- ---- [34m0073[m [1m0001[m [34mftsz[m|[31m0002[m true [1m0088[m [34mftsz[m|[31m0090[m [34m0095[m ]
0101 >  [35mint[m CONV   0092  [35mint[m.[34mnum[m index
0102    [35mint[m ADD    0101  [35m+1  [m
0103    [35mint[m FLOAD  0090  tab.asize
0104 >  [35mint[m ABC    0103  0102
0105    p64 FLOAD  0090  tab.array
0106    p64 AREF   0105  0102
0107 >  [34mnum[m ALOAD  0106
0108    [34mnum[m HSTORE 0091  0095
....        SNAP   #19  [ ---- ---- ---- ---- ---- true ---- ---- ---- [34m0073[m [1m0001[m [34mftsz[m|[31m0002[m true [34m0095[m [34m0107[m [35m+1  [m [35m0044[m [35m+1  [m [35m+1  [m ]
0109    [35mint[m FLOAD  0048  tab.asize
0110 >  [35mint[m ABC    0109  [35m+2  [m
0111    p64 FLOAD  0048  tab.array
0112    p64 AREF   0111  [35m+1  [m
0113 >  [31mtab[m ALOAD  0112
....        SNAP   #20  [ ---- ---- ---- ---- ---- true ---- ---- ---- [34m0073[m [1m0001[m [34mftsz[m|[31m0002[m true [34m0095[m [34m0107[m [35m+1  [m [35m0044[m [35m+1  [m [35m+1  [m [31m0113[m [31m0079[m ]
0114 >  [31mtab[m EQ     0113  0079
....        SNAP   #21  [ ---- ---- ---- ---- ---- true ---- ---- ---- [34m0073[m [1m0001[m [34mftsz[m|[31m0002[m true [34m0095[m [34m0107[m [35m+2  [m [35m0044[m [35m+1  [m [35m+2  [m ]
0115    p64 AREF   0111  [35m+2  [m
0116 >  [31mtab[m ALOAD  0115
....        SNAP   #22  [ ---- ---- ---- ---- ---- true ---- ---- ---- [34m0073[m [1m0001[m [34mftsz[m|[31m0002[m true [34m0095[m [34m0107[m [35m+2  [m [35m0044[m [35m+1  [m [35m+2  [m [31m0116[m [31m0079[m ]
0117 >  [31mtab[m NE     0116  0079
0118    [31mtab[m FLOAD  0116  tab.meta
0119 >  [31mtab[m EQ     0118  [31mNULL[m
0120    [35mint[m ALEN   0116  nil 
0121 >  [35mint[m ADDOV  0120  [35m+1  [m
0122    [35mint[m ADD    0120  [35m+1  [m
0123    [35mint[m FLOAD  0116  tab.asize
0124 >  [35mint[m ULE    0123  0122
0125    [35mint[m FLOAD  0116  tab.hmask
0126 >  [35mint[m EQ     0125  [35m+0  [m
0127    [34mnum[m CONV   0121  [34mnum[m.[35mint[m
0128    p64 NEWREF 0116  0127
0129    [34mnum[m HSTORE 0128  0107
0130  + [34mnum[m ADD    0107  0073
0131    [34mnum[m PHI    0073  0130
---- TRACE 14 stop -> loop

---- TRACE 15 start 14/11 triplet_old.lua:581
0033  . ISEQV    8   9
0034  . JMP      8 => 0042
0035  . UGET     8   2      ; buffers
0036  . TGETV    8   8   7
0037  . UGET     9   2      ; buffers
0038  . TGETV    9   9   7
0039  . LEN      9   9
0040  . ADDVN    9   9   0  ; 1
0041  . TSETV    3   8   9
0042  . FORL     4 => 0030
0043  . KPRI     4   2
0044  . MOV      5   3
0045  . RET      4   3
0019  ISNEP    8   0
0020  JMP     10 => 0022
0022  MOV      3   8
0023  ADDVV    7   7   9
0024  JMP      8 => 0014
0014  JLOOP    8   3
---- TRACE 15 IR
0001    [1mfun[m SLOAD  #10   PI
0002    [31mtab[m SLOAD  #12   PI
0003    [34mnum[m SLOAD  #14   PI
0004    [34mnum[m SLOAD  #15   PI
0005    [35mint[m SLOAD  #17   PI
0006    [31mtab[m SLOAD  #20   PI
0007    [31mtab[m SLOAD  #21   PI
....        SNAP   #0   [ ---- ---- ---- ---- ---- true ---- ---- ---- ---- [1m0001[m [34mftsz[m|[31m0002[m true [34m0003[m [34m0004[m [35m+2  [m [35m0005[m [35m+1  [m [35m+2  [m [31m0006[m [31m0007[m ]
....        SNAP   #1   [ ---- ---- ---- ---- ---- true ---- ---- ---- ---- [1m0001[m [34mftsz[m|[31m0002[m true [34m0003[m [34m0004[m [35m+2  [m [35m0005[m [35m+1  [m [35m+2  [m [31m0006[m [31m0007[m ]
0009 >  [31mtab[m NE     0007  0006
0010    [31mtab[m FLOAD  0006  tab.meta
0011 >  [31mtab[m EQ     0010  [31mNULL[m
0012 >  p64 UREFC  0001  #2  
0013 >  [31mtab[m ULOAD  0012
0014    [35mint[m FLOAD  0013  tab.asize
0015 >  [35mint[m ABC    0014  [35m+2  [m
0016    p64 FLOAD  0013  tab.array
0017    p64 AREF   0016  [35m+2  [m
0018 >  [31mtab[m ALOAD  0017
0019    [31mtab[m FLOAD  0018  tab.meta
0020 >  [31mtab[m EQ     0019  [31mNULL[m
0021    [35mint[m ALEN   0018  nil 
0022 >  [35mint[m ADDOV  0021  [35m+1  [m
0023    [35mint[m ADD    0021  [35m+1  [m
0024    [35mint[m FLOAD  0018  tab.asize
0025 >  [35mint[m ABC    0024  0023
0026    p64 FLOAD  0018  tab.array
0027    p64 AREF   0026  0023
0028    [34mnum[m ASTORE 0027  0004
....        SNAP   #2   [ ---- ---- ---- ---- ---- true ---- ---- ---- ---- [1m0001[m [34mftsz[m|[31m0002[m true [34m0003[m [34m0004[m [35m+3  [m [35m0005[m [35m+1  [m [35m+3  [m ]
0029 >  [35mint[m LT     0005  [35m+3  [m
....        SNAP   #3   [ ---- ---- ---- ---- ---- true ---- ---- ---- ---- [1m0001[m [34mftsz[m|---- ---- ---- [34m0004[m ]
0030 >  [34mnum[m SLOAD  #9    T
0031    [34mnum[m ADD    0030  0004
....        SNAP   #4   [ ---- ---- ---- ---- ---- true ---- ---- ---- [34m0031[m ]
---- TRACE 15 stop -> 3

---- TRACE 16 start 14/22 triplet_old.lua:581
0033  . ISEQV    8   9
0034  . JMP      8 => 0042
0035  . UGET     8   2      ; buffers
0036  . TGETV    8   8   7
0037  . UGET     9   2      ; buffers
0038  . TGETV    9   9   7
0039  . LEN      9   9
0040  . ADDVN    9   9   0  ; 1
0041  . TSETV    3   8   9
0042  . FORL     4 => 0030
0043  . KPRI     4   2
0044  . MOV      5   3
0045  . RET      4   3
0019  ISNEP    8   0
0020  JMP     10 => 0022
0022  MOV      3   8
0023  ADDVV    7   7   9
0024  JMP      8 => 0014
0014  JLOOP    8   3
---- TRACE 16 IR
0001    [34mnum[m SLOAD  #9    PI
0002    [1mfun[m SLOAD  #10   PI
0003    [31mtab[m SLOAD  #12   PI
0004    [34mnum[m SLOAD  #14   PI
0005    [34mnum[m SLOAD  #15   PI
0006    [35mint[m SLOAD  #17   PI
0007    [31mtab[m SLOAD  #20   PI
0008    [31mtab[m SLOAD  #21   PI
....        SNAP   #0   [ ---- ---- ---- ---- ---- true ---- ---- ---- [34m0001[m [1m0002[m [34mftsz[m|[31m0003[m true [34m0004[m [34m0005[m [35m+2  [m [35m0006[m [35m+1  [m [35m+2  [m [31m0007[m [31m0008[m ]
....        SNAP   #1   [ ---- ---- ---- ---- ---- true ---- ---- ---- [34m0001[m [1m0002[m [34mftsz[m|[31m0003[m true [34m0004[m [34m0005[m [35m+2  [m [35m0006[m [35m+1  [m [35m+2  [m [31m0007[m [31m0008[m ]
0010 >  [31mtab[m NE     0008  0007
0011    [31mtab[m FLOAD  0007  tab.meta
0012 >  [31mtab[m EQ     0011  [31mNULL[m
0013 >  p64 UREFC  0002  #2  
0014 >  [31mtab[m ULOAD  0013
0015    [35mint[m FLOAD  0014  tab.asize
0016 >  [35mint[m ABC    0015  [35m+2  [m
0017    p64 FLOAD  0014  tab.array
0018    p64 AREF   0017  [35m+2  [m
0019 >  [31mtab[m ALOAD  0018
0020    [31mtab[m FLOAD  0019  tab.meta
0021 >  [31mtab[m EQ     0020  [31mNULL[m
0022    [35mint[m ALEN   0019  nil 
0023 >  [35mint[m ADDOV  0022  [35m+1  [m
0024    [35mint[m ADD    0022  [35m+1  [m
0025    [35mint[m FLOAD  0019  tab.asize
0026 >  [35mint[m ABC    0025  0024
0027    p64 FLOAD  0019  tab.array
0028    p64 AREF   0027  0024
0029    [34mnum[m ASTORE 0028  0005
....        SNAP   #2   [ ---- ---- ---- ---- ---- true ---- ---- ---- [34m0001[m [1m0002[m [34mftsz[m|[31m0003[m true [34m0004[m [34m0005[m [35m+3  [m [35m0006[m [35m+1  [m [35m+3  [m ]
0030 >  [35mint[m LT     0006  [35m+3  [m
0031    [34mnum[m ADD    0005  0001
....        SNAP   #3   [ ---- ---- ---- ---- ---- true ---- ---- ---- [34m0031[m ]
---- TRACE 16 stop -> 3

---- TRACE 17 start 14/3 triplet_old.lua:35
0005  . . KPRI     2   0
0006  . . RET1     2   2
0020  . ISNEP    2   0
0021  . JMP      4 => 0024
0022  . KPRI     4   0
0023  . RET1     4   2
0019  ISNEP    8   0
0020  JMP     10 => 0022
0021  JMP      8 => 0025
0025  LOOP     8 => 0036
0026  MOV      8   4
0027  MOV     10   5
0028  MOV     11   6
0029  CALL     8   3   3
0000  . FUNCF   10          ; triplet_old.lua:572
0001  . TGETS    2   0   0  ; "buf"
0002  . LEN      2   2
0003  . KSHORT   3   0
0004  . ISGE     3   2
0005  . JMP      2 => 0013
0006  . KPRI     2   2
0007  . GGET     3   1      ; "table"
0008  . TGETS    3   3   2  ; "remove"
0009  . TGETS    5   0   0  ; "buf"
0010  . KSHORT   6   1
0011  . CALL     3   0   3
0000  . . FUNCF   10          ; builtin:remove
0001  . . ISTYPE   0  12
0002  . . LEN      2   0
0003  . . ISNEP    1   0
0004  . . JMP      3 => 0012
0012  . . ISNUM    1  15
0013  . . KSHORT   3   1
0014  . . ISGT     3   1
0015  . . JMP      3 => 0030
0016  . . ISGT     1   2
0017  . . JMP      3 => 0030
0018  . . TGETR    3   0   1
0019  . . ADDVN    4   1   1  ; 1
0020  . . MOV      5   2
0021  . . KSHORT   6   1
0022  . . JFORI    4 => 0027
---- TRACE 17 IR
0001    [1mfun[m SLOAD  #10   PI
0002    [31mtab[m SLOAD  #12   PI
0003    [1mfun[m SLOAD  #14   PI
....        SNAP   #0   [ ---- ---- ---- ---- ---- true ---- ---- ---- ---- [1m0001[m [34mftsz[m|[31m0002[m true [1m0003[m [34mftsz[m|---- ---- ]
0004 >  [1mfun[m SLOAD  #6    T
0005 >  [31mtab[m SLOAD  #7    T
0006 >  tru SLOAD  #8    T
0007    p64 FLOAD  0004  func.pc
0008 >  p64 EQ     0007  [0x7f38e8111fc8]
0009    [35mint[m FLOAD  0005  tab.hmask
0010 >  [35mint[m EQ     0009  [35m+1  [m
0011    p64 FLOAD  0005  tab.node
0012 >  p64 HREFK  0011  [32m"buf"[m @1
0013 >  [31mtab[m HLOAD  0012
0014    [31mtab[m FLOAD  0013  tab.meta
0015 >  [31mtab[m EQ     0014  [31mNULL[m
0016    [35mint[m ALEN   0013  nil 
....        SNAP   #1   [ ---- ---- ---- ---- ---- true ---- ---- true ---- [1m0004[m [34mftsz[m|[31m0005[m true ]
0017 >  [35mint[m GT     0016  [35m+0  [m
....        SNAP   #2   [ ---- ---- ---- ---- ---- true ---- ---- true ---- [1m0004[m [34mftsz[m|[31m0005[m ---- ]
0018    [31mtab[m FLOAD  0004  func.env
0019    [35mint[m FLOAD  0018  tab.hmask
0020 >  [35mint[m EQ     0019  [35m+63 [m
0021    p64 FLOAD  0018  tab.node
0022 >  p64 HREFK  0021  [32m"table"[m @14
0023 >  [31mtab[m HLOAD  0022
0024    [35mint[m FLOAD  0023  tab.hmask
0025 >  [35mint[m EQ     0024  [35m+15 [m
0026    p64 FLOAD  0023  tab.node
0027 >  p64 HREFK  0026  [32m"remove"[m @12
0028 >  [1mfun[m HLOAD  0027
0029 >  [1mfun[m EQ     0028  [1mbuiltin:remove[m
0030    [34mnum[m CONV   0016  [34mnum[m.[35mint[m
....        SNAP   #3   [ ---- ---- ---- ---- ---- true ---- ---- true ---- [1m0004[m [34mftsz[m|[31m0005[m ---- true [1mbuiltin:remove[m [34mftsz[m|---- ---- ---- ]
0031 >  [34mnum[m GE     0030  [34m+1  [m
....        SNAP   #4   [ ---- ---- ---- ---- ---- true ---- ---- true ---- [1m0004[m [34mftsz[m|[31m0005[m ---- true [1mbuiltin:remove[m [34mftsz[m|[31m0013[m [34m+1  [m [35m0016[m ]
0032    [35mint[m FLOAD  0013  tab.asize
0033 >  [35mint[m ABC    0032  [35m+1  [m
0034    p64 FLOAD  0013  tab.array
0035    p64 AREF   0034  [35m+1  [m
0036 >  [34mnum[m ALOAD  0035
....        SNAP   #5   [ ---- ---- ---- ---- ---- true ---- ---- true ---- [1m0004[m [34mftsz[m|[31m0005[m ---- true [1mbuiltin:remove[m [34mftsz[m|[31m0013[m [34m+1  [m [35m0016[m [34m0036[m ]
0037 >  [34mnum[m GE     0030  [34m+2  [m
....        SNAP   #6   [ ---- ---- ---- ---- ---- true ---- ---- true ---- [1m0004[m [34mftsz[m|[31m0005[m ---- true [1mbuiltin:remove[m [34mftsz[m|[31m0013[m [34m+1  [m [34m0030[m [34m0036[m [34m+2  [m [34m0030[m [34m+1  [m [34m+2  [m ]
---- TRACE 17 stop -> 5

---- TRACE 18 start 13/0 triplet_bench_lib.lua:149
0030  ISNEP    8   0
0031  JMP     10 => 0033
0033  MOV      6   8
0034  ADDVV    7   7   9
0035  JMP      8 => 0025
0025  LOOP     8 => 0036
0026  MOV      8   4
0027  MOV     10   5
0028  MOV     11   6
0029  CALL     8   3   3
0000  . FUNCF   10          ; triplet_old.lua:572
0001  . TGETS    2   0   0  ; "buf"
0002  . LEN      2   2
0003  . KSHORT   3   0
0004  . ISGE     3   2
0005  . JMP      2 => 0013
0006  . KPRI     2   2
0007  . GGET     3   1      ; "table"
0008  . TGETS    3   3   2  ; "remove"
0009  . TGETS    5   0   0  ; "buf"
0010  . KSHORT   6   1
0011  . CALL     3   0   3
0000  . . FUNCF   10          ; builtin:remove
0001  . . ISTYPE   0  12
0002  . . LEN      2   0
0003  . . ISNEP    1   0
0004  . . JMP      3 => 0012
0012  . . ISNUM    1  15
0013  . . KSHORT   3   1
0014  . . ISGT     3   1
0015  . . JMP      3 => 0030
0016  . . ISGT     1   2
0017  . . JMP      3 => 0030
0018  . . TGETR    3   0   1
0019  . . ADDVN    4   1   1  ; 1
0020  . . MOV      5   2
0021  . . KSHORT   6   1
0022  . . JFORI    4 => 0027
---- TRACE 18 IR
0001    [34mnum[m SLOAD  #11   PI
....        SNAP   #0   [ ---- ---- ---- ---- ---- ---- ---- ---- ---- ---- true [34m0001[m ]
0002 >  [34mnum[m SLOAD  #9    T
0003    [34mnum[m ADD    0002  0001
0004 >  [1mfun[m SLOAD  #6    T
0005 >  [31mtab[m SLOAD  #7    T
0006    p64 FLOAD  0004  func.pc
0007 >  p64 EQ     0006  [0x7f38e8111fc8]
0008    [35mint[m FLOAD  0005  tab.hmask
0009 >  [35mint[m EQ     0008  [35m+1  [m
0010    p64 FLOAD  0005  tab.node
0011 >  p64 HREFK  0010  [32m"buf"[m @1
0012 >  [31mtab[m HLOAD  0011
0013    [31mtab[m FLOAD  0012  tab.meta
0014 >  [31mtab[m EQ     0013  [31mNULL[m
0015    [35mint[m ALEN   0012  nil 
....        SNAP   #1   [ ---- ---- ---- ---- ---- ---- ---- ---- true [34m0003[m [1m0004[m [34mftsz[m|[31m0005[m true ]
0016 >  [35mint[m GT     0015  [35m+0  [m
....        SNAP   #2   [ ---- ---- ---- ---- ---- ---- ---- ---- true [34m0003[m [1m0004[m [34mftsz[m|[31m0005[m ---- ]
0017    [31mtab[m FLOAD  0004  func.env
0018    [35mint[m FLOAD  0017  tab.hmask
0019 >  [35mint[m EQ     0018  [35m+63 [m
0020    p64 FLOAD  0017  tab.node
0021 >  p64 HREFK  0020  [32m"table"[m @14
0022 >  [31mtab[m HLOAD  0021
0023    [35mint[m FLOAD  0022  tab.hmask
0024 >  [35mint[m EQ     0023  [35m+15 [m
0025    p64 FLOAD  0022  tab.node
0026 >  p64 HREFK  0025  [32m"remove"[m @12
0027 >  [1mfun[m HLOAD  0026
0028 >  [1mfun[m EQ     0027  [1mbuiltin:remove[m
0029    [34mnum[m CONV   0015  [34mnum[m.[35mint[m
....        SNAP   #3   [ ---- ---- ---- ---- ---- ---- ---- ---- true [34m0003[m [1m0004[m [34mftsz[m|[31m0005[m ---- true [1mbuiltin:remove[m [34mftsz[m|---- ---- ---- ]
0030 >  [34mnum[m GE     0029  [34m+1  [m
....        SNAP   #4   [ ---- ---- ---- ---- ---- ---- ---- ---- true [34m0003[m [1m0004[m [34mftsz[m|[31m0005[m ---- true [1mbuiltin:remove[m [34mftsz[m|[31m0012[m [34m+1  [m [35m0015[m ]
0031    [35mint[m FLOAD  0012  tab.asize
0032 >  [35mint[m ABC    0031  [35m+1  [m
0033    p64 FLOAD  0012  tab.array
0034    p64 AREF   0033  [35m+1  [m
0035 >  [34mnum[m ALOAD  0034
....        SNAP   #5   [ ---- ---- ---- ---- ---- ---- ---- ---- true [34m0003[m [1m0004[m [34mftsz[m|[31m0005[m ---- true [1mbuiltin:remove[m [34mftsz[m|[31m0012[m [34m+1  [m [35m0015[m [34m0035[m ]
0036 >  [34mnum[m GE     0029  [34m+2  [m
....        SNAP   #6   [ ---- ---- ---- ---- ---- ---- ---- ---- true [34m0003[m [1m0004[m [34mftsz[m|[31m0005[m ---- true [1mbuiltin:remove[m [34mftsz[m|[31m0012[m [34m+1  [m [34m0029[m [34m0035[m [34m+2  [m [34m0029[m [34m+1  [m [34m+2  [m ]
---- TRACE 18 stop -> 5

---- TRACE 19 start 5/1 builtin:remove
0027  KPRI     4   0
0028  TSETR    4   0   2
0029  RET1     3   2
0012  RETM     2   1
0030  ISNEP    8   0
0031  JMP     10 => 0033
0033  MOV      6   8
0034  ADDVV    7   7   9
0035  JMP      8 => 0025
0025  LOOP     8 => 0036
0026  MOV      8   4
0027  MOV     10   5
0028  MOV     11   6
0029  CALL     8   3   3
0000  . FUNCF   10          ; triplet_old.lua:572
0001  . TGETS    2   0   0  ; "buf"
0002  . LEN      2   2
0003  . KSHORT   3   0
0004  . ISGE     3   2
0005  . JMP      2 => 0013
0006  . KPRI     2   2
0007  . GGET     3   1      ; "table"
0008  . TGETS    3   3   2  ; "remove"
0009  . TGETS    5   0   0  ; "buf"
0010  . KSHORT   6   1
0011  . CALL     3   0   3
0000  . . FUNCF   10          ; builtin:remove
0001  . . ISTYPE   0  12
0002  . . LEN      2   0
0003  . . ISNEP    1   0
0004  . . JMP      3 => 0012
0012  . . ISNUM    1  15
0013  . . KSHORT   3   1
0014  . . ISGT     3   1
0015  . . JMP      3 => 0030
0016  . . ISGT     1   2
0017  . . JMP      3 => 0030
0018  . . TGETR    3   0   1
0019  . . ADDVN    4   1   1  ; 1
0020  . . MOV      5   2
0021  . . KSHORT   6   1
0022  . . JFORI    4 => 0027
0027  . . KPRI     4   0
0028  . . TSETR    4   0   2
0029  . . RET1     3   2
0012  . RETM     2   1
0030  ISNEP    8   0
0031  JMP     10 => 0033
0033  MOV      6   8
0034  ADDVV    7   7   9
0035  JMP      8 => 0025
0025  LOOP     8 => 0036
0026  MOV      8   4
0027  MOV     10   5
0028  MOV     11   6
0029  CALL     8   3   3
0000  . FUNCF   10          ; triplet_old.lua:572
0001  . TGETS    2   0   0  ; "buf"
0002  . LEN      2   2
0003  . KSHORT   3   0
0004  . ISGE     3   2
0005  . JMP      2 => 0013
0013  . UGET     2   0      ; state
0014  . TGETS    2   2   3  ; "g"
0015  . UGET     4   0      ; state
0016  . TGETS    4   4   4  ; "p"
0017  . UGET     5   0      ; state
0018  . TGETS    5   5   5  ; "c"
0019  . CALL     2   3   3
0000  . . FUNCF    4          ; triplet_old.lua:33
0001  . . ADDVN    1   1   0  ; 1
0002  . . LEN      2   0
0003  . . ISGE     2   1
0004  . . JMP      2 => 0007
0005  . . KPRI     2   0
0006  . . RET1     2   2
0020  . ISNEP    2   0
0021  . JMP      4 => 0024
0022  . KPRI     4   0
0023  . RET1     4   2
0030  ISNEP    8   0
0031  JMP     10 => 0033
0032  JMP      8 => 0036
0036  RET1     7   2
0099  ADDVV   13  13  18
0100  FORL    14 => 0097
0097  MOV     18  12
0098  CALL    18   2   1
0000  . FUNCF    5          ; triplet_trace.lua:19
0001  . UGET     0   0      ; lib
0002  . TGETS    0   0   0  ; "run_once"
0003  . UGET     2   1      ; T
0004  . UGET     3   2      ; scenario_name
0005  . UGET     4   3      ; payload
0006  . CALLT    0   4
0000  . FUNCF    7          ; triplet_bench_lib.lua:426
0001  . UGET     3   0      ; M
0002  . TGETS    3   3   0  ; "get_scenario"
0003  . MOV      5   1
0004  . CALL     3   2   2
0000  . . FUNCF    8          ; triplet_bench_lib.lua:413
0001  . . UGET     1   0      ; scenarios
0002  . . TGETV    1   1   0
0003  . . IST          1
0004  . . JMP      2 => 0013
0013  . . RET1     1   2
0005  . TGETS    3   3   1  ; "run_once"
0006  . MOV      5   0
0007  . MOV      6   2
0008  . CALLT    3   3
0000  . FUNCF    8          ; triplet_bench_lib.lua:358
0001  . TGETS    2   0   0  ; "tee"
0002  . KSHORT   4   2
0003  . TGETS    5   0   1  ; "seq"
0004  . TGETS    7   1   2  ; "values"
0005  . CALL     5   0   2
0000  . . FUNCF    4          ; triplet_old.lua:32
0001  . . FNEW     1   0      ; triplet_old.lua:33
---- TRACE 19 abort triplet_old.lua:37 -- NYI: bytecode FNEW  

---- TRACE 19 start 5/1 builtin:remove
0027  KPRI     4   0
0028  TSETR    4   0   2
0029  RET1     3   2
0012  RETM     2   1
0030  ISNEP    8   0
0031  JMP     10 => 0033
0033  MOV      6   8
0034  ADDVV    7   7   9
0035  JMP      8 => 0025
0025  LOOP     8 => 0036
0026  MOV      8   4
0027  MOV     10   5
0028  MOV     11   6
0029  CALL     8   3   3
0000  . FUNCF   10          ; triplet_old.lua:572
0001  . TGETS    2   0   0  ; "buf"
0002  . LEN      2   2
0003  . KSHORT   3   0
0004  . ISGE     3   2
0005  . JMP      2 => 0013
0006  . KPRI     2   2
0007  . GGET     3   1      ; "table"
0008  . TGETS    3   3   2  ; "remove"
0009  . TGETS    5   0   0  ; "buf"
0010  . KSHORT   6   1
0011  . CALL     3   0   3
0000  . . FUNCF   10          ; builtin:remove
0001  . . ISTYPE   0  12
0002  . . LEN      2   0
0003  . . ISNEP    1   0
0004  . . JMP      3 => 0012
0012  . . ISNUM    1  15
0013  . . KSHORT   3   1
0014  . . ISGT     3   1
0015  . . JMP      3 => 0030
0016  . . ISGT     1   2
0017  . . JMP      3 => 0030
0018  . . TGETR    3   0   1
0019  . . ADDVN    4   1   1  ; 1
0020  . . MOV      5   2
0021  . . KSHORT   6   1
0022  . . JFORI    4 => 0027
0027  . . KPRI     4   0
0028  . . TSETR    4   0   2
0029  . . RET1     3   2
0012  . RETM     2   1
0030  ISNEP    8   0
0031  JMP     10 => 0033
0033  MOV      6   8
0034  ADDVV    7   7   9
0035  JMP      8 => 0025
0025  LOOP     8 => 0036
0026  MOV      8   4
0027  MOV     10   5
0028  MOV     11   6
0029  CALL     8   3   3
0000  . FUNCF   10          ; triplet_old.lua:572
0001  . TGETS    2   0   0  ; "buf"
0002  . LEN      2   2
0003  . KSHORT   3   0
0004  . ISGE     3   2
0005  . JMP      2 => 0013
0013  . UGET     2   0      ; state
0014  . TGETS    2   2   3  ; "g"
0015  . UGET     4   0      ; state
0016  . TGETS    4   4   4  ; "p"
0017  . UGET     5   0      ; state
0018  . TGETS    5   5   5  ; "c"
0019  . CALL     2   3   3
0000  . . FUNCF    4          ; triplet_old.lua:33
0001  . . ADDVN    1   1   0  ; 1
0002  . . LEN      2   0
0003  . . ISGE     2   1
0004  . . JMP      2 => 0007
0005  . . KPRI     2   0
0006  . . RET1     2   2
0020  . ISNEP    2   0
0021  . JMP      4 => 0024
0022  . KPRI     4   0
0023  . RET1     4   2
0030  ISNEP    8   0
0031  JMP     10 => 0033
0032  JMP      8 => 0036
0036  RET1     7   2
0099  ADDVV   13  13  18
0100  FORL    14 => 0097
0097  MOV     18  12
0098  CALL    18   2   1
0000  . FUNCF    5          ; triplet_trace.lua:19
0001  . UGET     0   0      ; lib
0002  . TGETS    0   0   0  ; "run_once"
0003  . UGET     2   1      ; T
0004  . UGET     3   2      ; scenario_name
0005  . UGET     4   3      ; payload
0006  . CALLT    0   4
0000  . FUNCF    7          ; triplet_bench_lib.lua:426
0001  . UGET     3   0      ; M
0002  . TGETS    3   3   0  ; "get_scenario"
0003  . MOV      5   1
0004  . CALL     3   2   2
0000  . . FUNCF    8          ; triplet_bench_lib.lua:413
0001  . . UGET     1   0      ; scenarios
0002  . . TGETV    1   1   0
0003  . . IST          1
0004  . . JMP      2 => 0013
0013  . . RET1     1   2
0005  . TGETS    3   3   1  ; "run_once"
0006  . MOV      5   0
0007  . MOV      6   2
0008  . CALLT    3   3
0000  . FUNCF    8          ; triplet_bench_lib.lua:358
0001  . TGETS    2   0   0  ; "tee"
0002  . KSHORT   4   2
0003  . TGETS    5   0   1  ; "seq"
0004  . TGETS    7   1   2  ; "values"
0005  . CALL     5   0   2
0000  . . FUNCF    4          ; triplet_old.lua:32
0001  . . FNEW     1   0      ; triplet_old.lua:33
---- TRACE 19 abort triplet_old.lua:37 -- NYI: bytecode FNEW  

---- TRACE 19 start 5/1 builtin:remove
---- TRACE 19 IR
....        SNAP   #0   [ ---- ---- ---- ---- ---- ---- ]
....        SNAP   #1   [ ---- ---- ---- ---- ---- ---- ]
---- TRACE 19 stop -> interpreter

---- TRACE 20 start triplet_bench_lib.lua:147
0026  MOV      8   4
0027  MOV     10   5
0028  MOV     11   6
0029  CALL     8   3   3
0000  . FUNCF   10          ; triplet_old.lua:572
0001  . TGETS    2   0   0  ; "buf"
0002  . LEN      2   2
0003  . KSHORT   3   0
0004  . ISGE     3   2
0005  . JMP      2 => 0013
0006  . KPRI     2   2
0007  . GGET     3   1      ; "table"
0008  . TGETS    3   3   2  ; "remove"
0009  . TGETS    5   0   0  ; "buf"
0010  . KSHORT   6   1
0011  . CALL     3   0   3
0000  . . FUNCF   10          ; builtin:remove
0001  . . ISTYPE   0  12
0002  . . LEN      2   0
0003  . . ISNEP    1   0
0004  . . JMP      3 => 0012
0012  . . ISNUM    1  15
0013  . . KSHORT   3   1
0014  . . ISGT     3   1
0015  . . JMP      3 => 0030
0016  . . ISGT     1   2
0017  . . JMP      3 => 0030
0018  . . TGETR    3   0   1
0019  . . ADDVN    4   1   1  ; 1
0020  . . MOV      5   2
0021  . . KSHORT   6   1
0022  . . JFORI    4 => 0027
0027  . . KPRI     4   0
0028  . . TSETR    4   0   2
0029  . . RET1     3   2
0012  . RETM     2   1
0030  ISNEP    8   0
0031  JMP     10 => 0033
0033  MOV      6   8
0034  ADDVV    7   7   9
0035  JMP      8 => 0025
0025  LOOP     8 => 0036
---- TRACE 20 IR
....        SNAP   #0   [ ---- ---- ---- ---- ---- ---- ---- ---- ---- ---- ]
0001 >  [1mfun[m SLOAD  #6    T
0002 >  [31mtab[m SLOAD  #7    T
0003 >  tru SLOAD  #8    T
0004    p64 FLOAD  0001  func.pc
0005 >  p64 EQ     0004  [0x7f38e8111fc8]
0006    [35mint[m FLOAD  0002  tab.hmask
0007 >  [35mint[m EQ     0006  [35m+1  [m
0008    p64 FLOAD  0002  tab.node
0009 >  p64 HREFK  0008  [32m"buf"[m @1
0010 >  [31mtab[m HLOAD  0009
0011    [31mtab[m FLOAD  0010  tab.meta
0012 >  [31mtab[m EQ     0011  [31mNULL[m
0013    [35mint[m ALEN   0010  nil 
....        SNAP   #1   [ ---- ---- ---- ---- ---- ---- ---- ---- true ---- [1m0001[m [34mftsz[m|[31m0002[m true ]
0014 >  [35mint[m GT     0013  [35m+0  [m
....        SNAP   #2   [ ---- ---- ---- ---- ---- ---- ---- ---- true ---- [1m0001[m [34mftsz[m|[31m0002[m ---- ]
0015    [31mtab[m FLOAD  0001  func.env
0016    [35mint[m FLOAD  0015  tab.hmask
0017 >  [35mint[m EQ     0016  [35m+63 [m
0018    p64 FLOAD  0015  tab.node
0019 >  p64 HREFK  0018  [32m"table"[m @14
0020 >  [31mtab[m HLOAD  0019
0021    [35mint[m FLOAD  0020  tab.hmask
0022 >  [35mint[m EQ     0021  [35m+15 [m
0023    p64 FLOAD  0020  tab.node
0024 >  p64 HREFK  0023  [32m"remove"[m @12
0025 >  [1mfun[m HLOAD  0024
0026 >  [1mfun[m EQ     0025  [1mbuiltin:remove[m
0027    [34mnum[m CONV   0013  [34mnum[m.[35mint[m
....        SNAP   #3   [ ---- ---- ---- ---- ---- ---- ---- ---- true ---- [1m0001[m [34mftsz[m|[31m0002[m ---- true [1mbuiltin:remove[m [34mftsz[m|---- ---- ---- ]
0028 >  [34mnum[m GE     0027  [34m+1  [m
....        SNAP   #4   [ ---- ---- ---- ---- ---- ---- ---- ---- true ---- [1m0001[m [34mftsz[m|[31m0002[m ---- true [1mbuiltin:remove[m [34mftsz[m|[31m0010[m [34m+1  [m [35m0013[m ]
0029    [35mint[m FLOAD  0010  tab.asize
0030 >  [35mint[m ABC    0029  [35m+1  [m
0031    p64 FLOAD  0010  tab.array
0032    p64 AREF   0031  [35m+1  [m
0033 >  [34mnum[m ALOAD  0032
....        SNAP   #5   [ ---- ---- ---- ---- ---- ---- ---- ---- true ---- [1m0001[m [34mftsz[m|[31m0002[m ---- true [1mbuiltin:remove[m [34mftsz[m|[31m0010[m [34m+1  [m [35m0013[m [34m0033[m [34m+2  [m [34m0027[m [34m+1  [m [34m+2  [m ]
0034 >  [34mnum[m LT     0027  [34m+2  [m
....        SNAP   #6   [ ---- ---- ---- ---- ---- ---- ---- ---- true ---- [1m0001[m [34mftsz[m|[31m0002[m ---- true [1mbuiltin:remove[m [34mftsz[m|[31m0010[m ---- [35m0013[m [34m0033[m ]
0035 >  [35mint[m ABC    0029  0013
0036    p64 AREF   0031  0013
0037    nil ASTORE 0036  nil 
....        SNAP   #7   [ ---- ---- ---- ---- ---- ---- ---- ---- true ---- [1m0001[m [34mftsz[m|[31m0002[m ---- true [1mbuiltin:remove[m [34mftsz[m|---- ---- ---- [34m0033[m ---- ]
0038 >  [34mnum[m SLOAD  #9    T
0039  + [34mnum[m ADD    0038  0033
....        SNAP   #8   [ ---- ---- ---- ---- ---- ---- ---- ---- true [34m0039[m ]
0040 ------ LOOP ------------
0041    [35mint[m ALEN   0010  nil 
....        SNAP   #9   [ ---- ---- ---- ---- ---- ---- ---- ---- true [34m0039[m [1m0001[m [34mftsz[m|[31m0002[m true ]
0042 >  [35mint[m GT     0041  [35m+0  [m
0043    [34mnum[m CONV   0041  [34mnum[m.[35mint[m
....        SNAP   #10  [ ---- ---- ---- ---- ---- ---- ---- ---- true [34m0039[m [1m0001[m [34mftsz[m|[31m0002[m ---- true [1mbuiltin:remove[m [34mftsz[m|---- ---- ---- ]
0044 >  [34mnum[m GE     0043  [34m+1  [m
....        SNAP   #11  [ ---- ---- ---- ---- ---- ---- ---- ---- true [34m0039[m [1m0001[m [34mftsz[m|[31m0002[m ---- true [1mbuiltin:remove[m [34mftsz[m|[31m0010[m [34m+1  [m [35m0041[m ]
0045 >  [34mnum[m ALOAD  0032
....        SNAP   #12  [ ---- ---- ---- ---- ---- ---- ---- ---- true [34m0039[m [1m0001[m [34mftsz[m|[31m0002[m ---- true [1mbuiltin:remove[m [34mftsz[m|[31m0010[m [34m+1  [m [35m0041[m [34m0045[m [34m+2  [m [34m0043[m [34m+1  [m [34m+2  [m ]
0046 >  [34mnum[m LT     0043  [34m+2  [m
....        SNAP   #13  [ ---- ---- ---- ---- ---- ---- ---- ---- true [34m0039[m [1m0001[m [34mftsz[m|[31m0002[m ---- true [1mbuiltin:remove[m [34mftsz[m|[31m0010[m ---- [35m0041[m [34m0045[m ]
0047 >  [35mint[m ABC    0029  0041
0048    p64 AREF   0031  0041
0049    nil ASTORE 0048  nil 
0050  + [34mnum[m ADD    0045  0039
0051    [34mnum[m PHI    0039  0050
---- TRACE 20 stop -> loop

---- TRACE 21 start 20/1 triplet_old.lua:576
0013  . UGET     2   0      ; state
0014  . TGETS    2   2   3  ; "g"
0015  . UGET     4   0      ; state
0016  . TGETS    4   4   4  ; "p"
0017  . UGET     5   0      ; state
0018  . TGETS    5   5   5  ; "c"
0019  . CALL     2   3   3
0000  . . FUNCF    4          ; triplet_old.lua:33
0001  . . ADDVN    1   1   0  ; 1
0002  . . LEN      2   0
0003  . . ISGE     2   1
0004  . . JMP      2 => 0007
0005  . . KPRI     2   0
0006  . . RET1     2   2
0020  . ISNEP    2   0
0021  . JMP      4 => 0024
0022  . KPRI     4   0
0023  . RET1     4   2
0030  ISNEP    8   0
0031  JMP     10 => 0033
0032  JMP      8 => 0036
0036  RET1     7   2
0099  ADDVV   13  13  18
0100  FORL    14 => 0097
0097  MOV     18  12
0098  CALL    18   2   1
0000  . FUNCF    5          ; triplet_trace.lua:19
0001  . UGET     0   0      ; lib
0002  . TGETS    0   0   0  ; "run_once"
0003  . UGET     2   1      ; T
0004  . UGET     3   2      ; scenario_name
0005  . UGET     4   3      ; payload
0006  . CALLT    0   4
0000  . FUNCF    7          ; triplet_bench_lib.lua:426
0001  . UGET     3   0      ; M
0002  . TGETS    3   3   0  ; "get_scenario"
0003  . MOV      5   1
0004  . CALL     3   2   2
0000  . . FUNCF    8          ; triplet_bench_lib.lua:413
0001  . . UGET     1   0      ; scenarios
0002  . . TGETV    1   1   0
0003  . . IST          1
0004  . . JMP      2 => 0013
0013  . . RET1     1   2
0005  . TGETS    3   3   1  ; "run_once"
0006  . MOV      5   0
0007  . MOV      6   2
0008  . CALLT    3   3
0000  . FUNCF    8          ; triplet_bench_lib.lua:358
0001  . TGETS    2   0   0  ; "tee"
0002  . KSHORT   4   2
0003  . TGETS    5   0   1  ; "seq"
0004  . TGETS    7   1   2  ; "values"
0005  . CALL     5   0   2
0000  . . FUNCF    4          ; triplet_old.lua:32
0001  . . FNEW     1   0      ; triplet_old.lua:33
---- TRACE 21 abort triplet_old.lua:37 -- NYI: bytecode FNEW  

---- TRACE 21 start 20/9 triplet_old.lua:576
0013  . UGET     2   0      ; state
0014  . TGETS    2   2   3  ; "g"
0015  . UGET     4   0      ; state
0016  . TGETS    4   4   4  ; "p"
0017  . UGET     5   0      ; state
0018  . TGETS    5   5   5  ; "c"
0019  . CALL     2   3   3
0000  . . FUNCF    4          ; triplet_old.lua:33
0001  . . ADDVN    1   1   0  ; 1
0002  . . LEN      2   0
0003  . . ISGE     2   1
0004  . . JMP      2 => 0007
0005  . . KPRI     2   0
0006  . . RET1     2   2
0020  . ISNEP    2   0
0021  . JMP      4 => 0024
0022  . KPRI     4   0
0023  . RET1     4   2
0030  ISNEP    8   0
0031  JMP     10 => 0033
0032  JMP      8 => 0036
0036  RET1     7   2
0099  ADDVV   13  13  18
0100  FORL    14 => 0097
0097  MOV     18  12
0098  CALL    18   2   1
0000  . FUNCF    5          ; triplet_trace.lua:19
0001  . UGET     0   0      ; lib
0002  . TGETS    0   0   0  ; "run_once"
0003  . UGET     2   1      ; T
0004  . UGET     3   2      ; scenario_name
0005  . UGET     4   3      ; payload
0006  . CALLT    0   4
0000  . FUNCF    7          ; triplet_bench_lib.lua:426
0001  . UGET     3   0      ; M
0002  . TGETS    3   3   0  ; "get_scenario"
0003  . MOV      5   1
0004  . CALL     3   2   2
0000  . . FUNCF    8          ; triplet_bench_lib.lua:413
0001  . . UGET     1   0      ; scenarios
0002  . . TGETV    1   1   0
0003  . . IST          1
0004  . . JMP      2 => 0013
0013  . . RET1     1   2
0005  . TGETS    3   3   1  ; "run_once"
0006  . MOV      5   0
0007  . MOV      6   2
0008  . CALLT    3   3
0000  . FUNCF    8          ; triplet_bench_lib.lua:358
0001  . TGETS    2   0   0  ; "tee"
0002  . KSHORT   4   2
0003  . TGETS    5   0   1  ; "seq"
0004  . TGETS    7   1   2  ; "values"
0005  . CALL     5   0   2
0000  . . FUNCF    4          ; triplet_old.lua:32
0001  . . FNEW     1   0      ; triplet_old.lua:33
---- TRACE 21 abort triplet_old.lua:37 -- NYI: bytecode FNEW  

---- TRACE 21 start 20/9 triplet_old.lua:576
0013  . UGET     2   0      ; state
0014  . TGETS    2   2   3  ; "g"
0015  . UGET     4   0      ; state
0016  . TGETS    4   4   4  ; "p"
0017  . UGET     5   0      ; state
0018  . TGETS    5   5   5  ; "c"
0019  . CALL     2   3   3
0000  . . FUNCF    4          ; triplet_old.lua:33
0001  . . ADDVN    1   1   0  ; 1
0002  . . LEN      2   0
0003  . . ISGE     2   1
0004  . . JMP      2 => 0007
0005  . . KPRI     2   0
0006  . . RET1     2   2
0020  . ISNEP    2   0
0021  . JMP      4 => 0024
0022  . KPRI     4   0
0023  . RET1     4   2
0030  ISNEP    8   0
0031  JMP     10 => 0033
0032  JMP      8 => 0036
0036  RET1     7   2
0099  ADDVV   13  13  18
0100  FORL    14 => 0097
0097  MOV     18  12
0098  CALL    18   2   1
0000  . FUNCF    5          ; triplet_trace.lua:19
0001  . UGET     0   0      ; lib
0002  . TGETS    0   0   0  ; "run_once"
0003  . UGET     2   1      ; T
0004  . UGET     3   2      ; scenario_name
0005  . UGET     4   3      ; payload
0006  . CALLT    0   4
0000  . FUNCF    7          ; triplet_bench_lib.lua:426
0001  . UGET     3   0      ; M
0002  . TGETS    3   3   0  ; "get_scenario"
0003  . MOV      5   1
0004  . CALL     3   2   2
0000  . . FUNCF    8          ; triplet_bench_lib.lua:413
0001  . . UGET     1   0      ; scenarios
0002  . . TGETV    1   1   0
0003  . . IST          1
0004  . . JMP      2 => 0013
0013  . . RET1     1   2
0005  . TGETS    3   3   1  ; "run_once"
0006  . MOV      5   0
0007  . MOV      6   2
0008  . CALLT    3   3
0000  . FUNCF    8          ; triplet_bench_lib.lua:358
0001  . TGETS    2   0   0  ; "tee"
0002  . KSHORT   4   2
0003  . TGETS    5   0   1  ; "seq"
0004  . TGETS    7   1   2  ; "values"
0005  . CALL     5   0   2
0000  . . FUNCF    4          ; triplet_old.lua:32
0001  . . FNEW     1   0      ; triplet_old.lua:33
---- TRACE 21 abort triplet_old.lua:37 -- NYI: bytecode FNEW  

---- TRACE 21 start 20/9 triplet_old.lua:576
0013  . UGET     2   0      ; state
0014  . TGETS    2   2   3  ; "g"
0015  . UGET     4   0      ; state
0016  . TGETS    4   4   4  ; "p"
0017  . UGET     5   0      ; state
0018  . TGETS    5   5   5  ; "c"
0019  . CALL     2   3   3
0000  . . FUNCF    4          ; triplet_old.lua:33
0001  . . ADDVN    1   1   0  ; 1
0002  . . LEN      2   0
0003  . . ISGE     2   1
0004  . . JMP      2 => 0007
0005  . . KPRI     2   0
0006  . . RET1     2   2
0020  . ISNEP    2   0
0021  . JMP      4 => 0024
0022  . KPRI     4   0
0023  . RET1     4   2
0030  ISNEP    8   0
0031  JMP     10 => 0033
0032  JMP      8 => 0036
0036  RET1     7   2
0099  ADDVV   13  13  18
0100  FORL    14 => 0097
0097  MOV     18  12
0098  CALL    18   2   1
0000  . FUNCF    5          ; triplet_trace.lua:19
0001  . UGET     0   0      ; lib
0002  . TGETS    0   0   0  ; "run_once"
0003  . UGET     2   1      ; T
0004  . UGET     3   2      ; scenario_name
0005  . UGET     4   3      ; payload
0006  . CALLT    0   4
0000  . FUNCF    7          ; triplet_bench_lib.lua:426
0001  . UGET     3   0      ; M
0002  . TGETS    3   3   0  ; "get_scenario"
0003  . MOV      5   1
0004  . CALL     3   2   2
0000  . . FUNCF    8          ; triplet_bench_lib.lua:413
0001  . . UGET     1   0      ; scenarios
0002  . . TGETV    1   1   0
0003  . . IST          1
0004  . . JMP      2 => 0013
0013  . . RET1     1   2
0005  . TGETS    3   3   1  ; "run_once"
0006  . MOV      5   0
0007  . MOV      6   2
0008  . CALLT    3   3
0000  . FUNCF    8          ; triplet_bench_lib.lua:358
0001  . TGETS    2   0   0  ; "tee"
0002  . KSHORT   4   2
0003  . TGETS    5   0   1  ; "seq"
0004  . TGETS    7   1   2  ; "values"
0005  . CALL     5   0   2
0000  . . FUNCF    4          ; triplet_old.lua:32
0001  . . FNEW     1   0      ; triplet_old.lua:33
---- TRACE 21 abort triplet_old.lua:37 -- NYI: bytecode FNEW  

---- TRACE 21 start 20/9 triplet_old.lua:576
0013  . UGET     2   0      ; state
0014  . TGETS    2   2   3  ; "g"
0015  . UGET     4   0      ; state
0016  . TGETS    4   4   4  ; "p"
0017  . UGET     5   0      ; state
0018  . TGETS    5   5   5  ; "c"
0019  . CALL     2   3   3
0000  . . FUNCF    4          ; triplet_old.lua:33
0001  . . ADDVN    1   1   0  ; 1
0002  . . LEN      2   0
0003  . . ISGE     2   1
0004  . . JMP      2 => 0007
0005  . . KPRI     2   0
0006  . . RET1     2   2
0020  . ISNEP    2   0
0021  . JMP      4 => 0024
0022  . KPRI     4   0
0023  . RET1     4   2
0030  ISNEP    8   0
0031  JMP     10 => 0033
0032  JMP      8 => 0036
0036  RET1     7   2
0099  ADDVV   13  13  18
0100  FORL    14 => 0097
0097  MOV     18  12
0098  CALL    18   2   1
0000  . FUNCF    5          ; triplet_trace.lua:19
0001  . UGET     0   0      ; lib
0002  . TGETS    0   0   0  ; "run_once"
0003  . UGET     2   1      ; T
0004  . UGET     3   2      ; scenario_name
0005  . UGET     4   3      ; payload
0006  . CALLT    0   4
0000  . FUNCF    7          ; triplet_bench_lib.lua:426
0001  . UGET     3   0      ; M
0002  . TGETS    3   3   0  ; "get_scenario"
0003  . MOV      5   1
0004  . CALL     3   2   2
0000  . . FUNCF    8          ; triplet_bench_lib.lua:413
0001  . . UGET     1   0      ; scenarios
0002  . . TGETV    1   1   0
0003  . . IST          1
0004  . . JMP      2 => 0013
0013  . . RET1     1   2
0005  . TGETS    3   3   1  ; "run_once"
0006  . MOV      5   0
0007  . MOV      6   2
0008  . CALLT    3   3
0000  . FUNCF    8          ; triplet_bench_lib.lua:358
0001  . TGETS    2   0   0  ; "tee"
0002  . KSHORT   4   2
0003  . TGETS    5   0   1  ; "seq"
0004  . TGETS    7   1   2  ; "values"
0005  . CALL     5   0   2
0000  . . FUNCF    4          ; triplet_old.lua:32
0001  . . FNEW     1   0      ; triplet_old.lua:33
---- TRACE 21 abort triplet_old.lua:37 -- NYI: bytecode FNEW  

---- TRACE 21 start 20/9 triplet_old.lua:576
---- TRACE 21 IR
0001    [34mnum[m SLOAD  #9    PI
0002    [1mfun[m SLOAD  #10   PI
0003    [31mtab[m SLOAD  #12   PI
....        SNAP   #0   [ ---- ---- ---- ---- ---- ---- ---- ---- true [34m0001[m [1m0002[m [34mftsz[m|[31m0003[m true ]
....        SNAP   #1   [ ---- ---- ---- ---- ---- ---- ---- ---- true [34m0001[m [1m0002[m [34mftsz[m|[31m0003[m true ]
---- TRACE 21 stop -> interpreter

---- TRACE 22 start triplet_trace.lua:31
0097  MOV     18  12
0098  CALL    18   2   1
0000  . FUNCF    5          ; triplet_trace.lua:19
0001  . UGET     0   0      ; lib
0002  . TGETS    0   0   0  ; "run_once"
0003  . UGET     2   1      ; T
0004  . UGET     3   2      ; scenario_name
0005  . UGET     4   3      ; payload
0006  . CALLT    0   4
0000  . FUNCF    7          ; triplet_bench_lib.lua:426
0001  . UGET     3   0      ; M
0002  . TGETS    3   3   0  ; "get_scenario"
0003  . MOV      5   1
0004  . CALL     3   2   2
0000  . . FUNCF    8          ; triplet_bench_lib.lua:413
0001  . . UGET     1   0      ; scenarios
0002  . . TGETV    1   1   0
0003  . . IST          1
0004  . . JMP      2 => 0013
0013  . . RET1     1   2
0005  . TGETS    3   3   1  ; "run_once"
0006  . MOV      5   0
0007  . MOV      6   2
0008  . CALLT    3   3
0000  . FUNCF    8          ; triplet_bench_lib.lua:358
0001  . TGETS    2   0   0  ; "tee"
0002  . KSHORT   4   2
0003  . TGETS    5   0   1  ; "seq"
0004  . TGETS    7   1   2  ; "values"
0005  . CALL     5   0   2
0000  . . FUNCF    4          ; triplet_old.lua:32
0001  . . FNEW     1   0      ; triplet_old.lua:33
---- TRACE 22 abort triplet_old.lua:37 -- NYI: bytecode FNEW  

---- TRACE 22 start triplet_trace.lua:19
0001  UGET     0   0      ; lib
0002  TGETS    0   0   0  ; "run_once"
0003  UGET     2   1      ; T
0004  UGET     3   2      ; scenario_name
0005  UGET     4   3      ; payload
0006  CALLT    0   4
0000  FUNCF    7          ; triplet_bench_lib.lua:426
0001  UGET     3   0      ; M
0002  TGETS    3   3   0  ; "get_scenario"
0003  MOV      5   1
0004  CALL     3   2   2
0000  . FUNCF    8          ; triplet_bench_lib.lua:413
0001  . UGET     1   0      ; scenarios
0002  . TGETV    1   1   0
0003  . IST          1
0004  . JMP      2 => 0013
0013  . RET1     1   2
0005  TGETS    3   3   1  ; "run_once"
0006  MOV      5   0
0007  MOV      6   2
0008  CALLT    3   3
0000  FUNCF    8          ; triplet_bench_lib.lua:358
0001  TGETS    2   0   0  ; "tee"
0002  KSHORT   4   2
0003  TGETS    5   0   1  ; "seq"
0004  TGETS    7   1   2  ; "values"
0005  CALL     5   0   2
0000  . FUNCF    4          ; triplet_old.lua:32
0001  . FNEW     1   0      ; triplet_old.lua:33
---- TRACE 22 abort triplet_old.lua:37 -- NYI: bytecode FNEW  

---- TRACE 22 start triplet_bench_lib.lua:426
0001  UGET     3   0      ; M
0002  TGETS    3   3   0  ; "get_scenario"
0003  MOV      5   1
0004  CALL     3   2   2
0000  . FUNCF    8          ; triplet_bench_lib.lua:413
0001  . UGET     1   0      ; scenarios
0002  . TGETV    1   1   0
0003  . IST          1
0004  . JMP      2 => 0013
0013  . RET1     1   2
0005  TGETS    3   3   1  ; "run_once"
0006  MOV      5   0
0007  MOV      6   2
0008  CALLT    3   3
0000  FUNCF    8          ; triplet_bench_lib.lua:358
0001  TGETS    2   0   0  ; "tee"
0002  KSHORT   4   2
0003  TGETS    5   0   1  ; "seq"
0004  TGETS    7   1   2  ; "values"
0005  CALL     5   0   2
0000  . FUNCF    4          ; triplet_old.lua:32
0001  . FNEW     1   0      ; triplet_old.lua:33
---- TRACE 22 abort triplet_old.lua:37 -- NYI: bytecode FNEW  

---- TRACE 22 start triplet_bench_lib.lua:358
0001  TGETS    2   0   0  ; "tee"
0002  KSHORT   4   2
0003  TGETS    5   0   1  ; "seq"
0004  TGETS    7   1   2  ; "values"
0005  CALL     5   0   2
0000  . FUNCF    4          ; triplet_old.lua:32
0001  . FNEW     1   0      ; triplet_old.lua:33
---- TRACE 22 abort triplet_old.lua:37 -- NYI: bytecode FNEW  

---- TRACE 22 start triplet_old.lua:589
0027  UCLO     0 => 0028
---- TRACE 22 abort triplet_old.lua:592 -- leaving loop in root trace

---- TRACE 22 start triplet_bench_lib.lua:413
0001  UGET     1   0      ; scenarios
0002  TGETV    1   1   0
0003  IST          1
0004  JMP      2 => 0013
0013  RET1     1   2
---- TRACE 22 IR
....        SNAP   #0   [ ---- ---- ---- ]
0001    [1mfun[m SLOAD  #0    R
0002 >  p64 UREFC  0001  #0  
0003 >  [31mtab[m ULOAD  0002
0004 >  [32mstr[m SLOAD  #2    T
0005    p64 HREF   0003  0004
0006 >  [31mtab[m HLOAD  0005
....        SNAP   #1   [ ---- ---- ---- [31m0006[m ]
---- TRACE 22 stop -> return

---- TRACE 23 start triplet_old.lua:570
0013  FNEW     6   4      ; triplet_old.lua:572
---- TRACE 23 abort triplet_old.lua:586 -- leaving loop in root trace

